Workbook

Sheet READ ME
A1: Instaprotek Portal - Regression QA Log
A2: Your test cases, one sheet per module, set up for logging results. This workbook is the QA log.
A4: How to log a run
A5: 1. Copy this workbook per release, e.g. Regression_QA_Log_<version>.xlsx.
A6: 2. In each module sheet set the 'Actual Result' column to Pass / Fail / Blocked / Not Tested / N/A (dropdown); put detail in 'Notes/Remarks'.
A7: 3. For any Fail, add a row on the DEFECT LOG tab and put its Defect ID in the 'Defect ID' column of the test row.
A8: 4. The SUMMARY tab totals pass/fail per module and overall automatically.
A10: Environment & login
A11: Test on QA-environment (qa.crm.instaprotek.com) with the QA login in credentials.json. Delete any test records you create when done - never against Production.
A13: Test data (registration)
A14: Product barcode to use: 810135810326
A15: Example device from past runs: Samsung, Model SM-A156UZKDXAA. Use a QA/test serial number and delete the record after testing.

Sheet SUMMARY
A1: Regression QA Log - Summary
A3: Total cases | B3: =B31 | D3: Pass rate (of executed) | E3: =IFERROR(C31/(C31+D31+E31),0)
A4: Executed | B4: =C31+D31+E31
A6: Module | B6: Total | C6: Pass | D6: Fail | E6: Blocked | F6: Not Tested | G6: N/A
A7: USERS | B7: =COUNTA(USERS!$B$2:$B$2000) | C7: =COUNTIF(USERS!$E$2:$E$2000,"Pass") | D7: =COUNTIF(USERS!$E$2:$E$2000,"Fail") | E7: =COUNTIF(USERS!$E$2:$E$2000,"Blocked") | F7: =COUNTIF(USERS!$E$2:$E$2000,"Not Tested") | G7: =COUNTIF(USERS!$E$2:$E$2000,"N/A")
A8: PORTAL - REGISTRATION | B8: =COUNTA('PORTAL - REGISTRATION'!$B$2:$B$2000) | C8: =COUNTIF('PORTAL - REGISTRATION'!$E$2:$E$2000,"Pass") | D8: =COUNTIF('PORTAL - REGISTRATION'!$E$2:$E$2000,"Fail") | E8: =COUNTIF('PORTAL - REGISTRATION'!$E$2:$E$2000,"Blocked") | F8: =COUNTIF('PORTAL - REGISTRATION'!$E$2:$E$2000,"Not Tested") | G8: =COUNTIF('PORTAL - REGISTRATION'!$E$2:$E$2000,"N/A")
A9: ORDERS | B9: =COUNTA(ORDERS!$B$2:$B$2000) | C9: =COUNTIF(ORDERS!$E$2:$E$2000,"Pass") | D9: =COUNTIF(ORDERS!$E$2:$E$2000,"Fail") | E9: =COUNTIF(ORDERS!$E$2:$E$2000,"Blocked") | F9: =COUNTIF(ORDERS!$E$2:$E$2000,"Not Tested") | G9: =COUNTIF(ORDERS!$E$2:$E$2000,"N/A")
A10: REPAIR SHOPS | B10: =COUNTA('REPAIR SHOPS'!$B$2:$B$2000) | C10: =COUNTIF('REPAIR SHOPS'!$E$2:$E$2000,"Pass") | D10: =COUNTIF('REPAIR SHOPS'!$E$2:$E$2000,"Fail") | E10: =COUNTIF('REPAIR SHOPS'!$E$2:$E$2000,"Blocked") | F10: =COUNTIF('REPAIR SHOPS'!$E$2:$E$2000,"Not Tested") | G10: =COUNTIF('REPAIR SHOPS'!$E$2:$E$2000,"N/A")
A11: AFFILIATES | B11: =COUNTA(AFFILIATES!$B$2:$B$2000) | C11: =COUNTIF(AFFILIATES!$E$2:$E$2000,"Pass") | D11: =COUNTIF(AFFILIATES!$E$2:$E$2000,"Fail") | E11: =COUNTIF(AFFILIATES!$E$2:$E$2000,"Blocked") | F11: =COUNTIF(AFFILIATES!$E$2:$E$2000,"Not Tested") | G11: =COUNTIF(AFFILIATES!$E$2:$E$2000,"N/A")
A12: CLAIM REPORTS | B12: =COUNTA('CLAIM REPORTS'!$B$2:$B$2000) | C12: =COUNTIF('CLAIM REPORTS'!$E$2:$E$2000,"Pass") | D12: =COUNTIF('CLAIM REPORTS'!$E$2:$E$2000,"Fail") | E12: =COUNTIF('CLAIM REPORTS'!$E$2:$E$2000,"Blocked") | F12: =COUNTIF('CLAIM REPORTS'!$E$2:$E$2000,"Not Tested") | G12: =COUNTIF('CLAIM REPORTS'!$E$2:$E$2000,"N/A")
A13: PRODUCT REVIEWS | B13: =COUNTA('PRODUCT REVIEWS'!$B$2:$B$2000) | C13: =COUNTIF('PRODUCT REVIEWS'!$E$2:$E$2000,"Pass") | D13: =COUNTIF('PRODUCT REVIEWS'!$E$2:$E$2000,"Fail") | E13: =COUNTIF('PRODUCT REVIEWS'!$E$2:$E$2000,"Blocked") | F13: =COUNTIF('PRODUCT REVIEWS'!$E$2:$E$2000,"Not Tested") | G13: =COUNTIF('PRODUCT REVIEWS'!$E$2:$E$2000,"N/A")
A14: DEVICE BUYBACK | B14: =COUNTA('DEVICE BUYBACK'!$B$2:$B$2000) | C14: =COUNTIF('DEVICE BUYBACK'!$E$2:$E$2000,"Pass") | D14: =COUNTIF('DEVICE BUYBACK'!$E$2:$E$2000,"Fail") | E14: =COUNTIF('DEVICE BUYBACK'!$E$2:$E$2000,"Blocked") | F14: =COUNTIF('DEVICE BUYBACK'!$E$2:$E$2000,"Not Tested") | G14: =COUNTIF('DEVICE BUYBACK'!$E$2:$E$2000,"N/A")
A15: SETTINGS - DEVICE CATEGORY | B15: =COUNTA('SETTINGS - DEVICE CATEGORY'!$B$2:$B$2000) | C15: =COUNTIF('SETTINGS - DEVICE CATEGORY'!$E$2:$E$2000,"Pass") | D15: =COUNTIF('SETTINGS - DEVICE CATEGORY'!$E$2:$E$2000,"Fail") | E15: =COUNTIF('SETTINGS - DEVICE CATEGORY'!$E$2:$E$2000,"Blocked") | F15: =COUNTIF('SETTINGS - DEVICE CATEGORY'!$E$2:$E$2000,"Not Tested") | G15: =COUNTIF('SETTINGS - DEVICE CATEGORY'!$E$2:$E$2000,"N/A")
A16: SETTINGS - PRODUCT CATEGORY | B16: =COUNTA('SETTINGS - PRODUCT CATEGORY '!$B$2:$B$2000) | C16: =COUNTIF('SETTINGS - PRODUCT CATEGORY '!$E$2:$E$2000,"Pass") | D16: =COUNTIF('SETTINGS - PRODUCT CATEGORY '!$E$2:$E$2000,"Fail") | E16: =COUNTIF('SETTINGS - PRODUCT CATEGORY '!$E$2:$E$2000,"Blocked") | F16: =COUNTIF('SETTINGS - PRODUCT CATEGORY '!$E$2:$E$2000,"Not Tested") | G16: =COUNTIF('SETTINGS - PRODUCT CATEGORY '!$E$2:$E$2000,"N/A")
A17: SETTINGS - BRAND | B17: =COUNTA('SETTINGS - BRAND'!$B$2:$B$2000) | C17: =COUNTIF('SETTINGS - BRAND'!$E$2:$E$2000,"Pass") | D17: =COUNTIF('SETTINGS - BRAND'!$E$2:$E$2000,"Fail") | E17: =COUNTIF('SETTINGS - BRAND'!$E$2:$E$2000,"Blocked") | F17: =COUNTIF('SETTINGS - BRAND'!$E$2:$E$2000,"Not Tested") | G17: =COUNTIF('SETTINGS - BRAND'!$E$2:$E$2000,"N/A")
A18: SETTINGS - REGISTRATION SURVEY | B18: =COUNTA('SETTINGS - REGISTRATION SURVEY '!$B$2:$B$2000) | C18: =COUNTIF('SETTINGS - REGISTRATION SURVEY '!$E$2:$E$2000,"Pass") | D18: =COUNTIF('SETTINGS - REGISTRATION SURVEY '!$E$2:$E$2000,"Fail") | E18: =COUNTIF('SETTINGS - REGISTRATION SURVEY '!$E$2:$E$2000,"Blocked") | F18: =COUNTIF('SETTINGS - REGISTRATION SURVEY '!$E$2:$E$2000,"Not Tested") | G18: =COUNTIF('SETTINGS - REGISTRATION SURVEY '!$E$2:$E$2000,"N/A")
A19: SETTINGS - PLAN | B19: =COUNTA('SETTINGS - PLAN '!$B$2:$B$2000) | C19: =COUNTIF('SETTINGS - PLAN '!$E$2:$E$2000,"Pass") | D19: =COUNTIF('SETTINGS - PLAN '!$E$2:$E$2000,"Fail") | E19: =COUNTIF('SETTINGS - PLAN '!$E$2:$E$2000,"Blocked") | F19: =COUNTIF('SETTINGS - PLAN '!$E$2:$E$2000,"Not Tested") | G19: =COUNTIF('SETTINGS - PLAN '!$E$2:$E$2000,"N/A")
A20: SETTINGS - REPAIR NETWORk | B20: =COUNTA('SETTINGS - REPAIR NETWORk '!$B$2:$B$2000) | C20: =COUNTIF('SETTINGS - REPAIR NETWORk '!$E$2:$E$2000,"Pass") | D20: =COUNTIF('SETTINGS - REPAIR NETWORk '!$E$2:$E$2000,"Fail") | E20: =COUNTIF('SETTINGS - REPAIR NETWORk '!$E$2:$E$2000,"Blocked") | F20: =COUNTIF('SETTINGS - REPAIR NETWORk '!$E$2:$E$2000,"Not Tested") | G20: =COUNTIF('SETTINGS - REPAIR NETWORk '!$E$2:$E$2000,"N/A")
A21: SETTINGS - COMPANY | B21: =COUNTA('SETTINGS - COMPANY '!$B$2:$B$2000) | C21: =COUNTIF('SETTINGS - COMPANY '!$E$2:$E$2000,"Pass") | D21: =COUNTIF('SETTINGS - COMPANY '!$E$2:$E$2000,"Fail") | E21: =COUNTIF('SETTINGS - COMPANY '!$E$2:$E$2000,"Blocked") | F21: =COUNTIF('SETTINGS - COMPANY '!$E$2:$E$2000,"Not Tested") | G21: =COUNTIF('SETTINGS - COMPANY '!$E$2:$E$2000,"N/A")
A22: SETTINGS - LANGUAGE | B22: =COUNTA('SETTINGS - LANGUAGE'!$B$2:$B$2000) | C22: =COUNTIF('SETTINGS - LANGUAGE'!$E$2:$E$2000,"Pass") | D22: =COUNTIF('SETTINGS - LANGUAGE'!$E$2:$E$2000,"Fail") | E22: =COUNTIF('SETTINGS - LANGUAGE'!$E$2:$E$2000,"Blocked") | F22: =COUNTIF('SETTINGS - LANGUAGE'!$E$2:$E$2000,"Not Tested") | G22: =COUNTIF('SETTINGS - LANGUAGE'!$E$2:$E$2000,"N/A")
A23: SETTINGS - REGIONS | B23: =COUNTA('SETTINGS - REGIONS'!$B$2:$B$2000) | C23: =COUNTIF('SETTINGS - REGIONS'!$E$2:$E$2000,"Pass") | D23: =COUNTIF('SETTINGS - REGIONS'!$E$2:$E$2000,"Fail") | E23: =COUNTIF('SETTINGS - REGIONS'!$E$2:$E$2000,"Blocked") | F23: =COUNTIF('SETTINGS - REGIONS'!$E$2:$E$2000,"Not Tested") | G23: =COUNTIF('SETTINGS - REGIONS'!$E$2:$E$2000,"N/A")
A24: SETTINGS - ADMINISTRATORS | B24: =COUNTA('SETTINGS - ADMINISTRATORS'!$B$2:$B$2000) | C24: =COUNTIF('SETTINGS - ADMINISTRATORS'!$E$2:$E$2000,"Pass") | D24: =COUNTIF('SETTINGS - ADMINISTRATORS'!$E$2:$E$2000,"Fail") | E24: =COUNTIF('SETTINGS - ADMINISTRATORS'!$E$2:$E$2000,"Blocked") | F24: =COUNTIF('SETTINGS - ADMINISTRATORS'!$E$2:$E$2000,"Not Tested") | G24: =COUNTIF('SETTINGS - ADMINISTRATORS'!$E$2:$E$2000,"N/A")
A25: SETTINGS - UNDERWRITERS | B25: =COUNTA('SETTINGS - UNDERWRITERS'!$B$2:$B$2000) | C25: =COUNTIF('SETTINGS - UNDERWRITERS'!$E$2:$E$2000,"Pass") | D25: =COUNTIF('SETTINGS - UNDERWRITERS'!$E$2:$E$2000,"Fail") | E25: =COUNTIF('SETTINGS - UNDERWRITERS'!$E$2:$E$2000,"Blocked") | F25: =COUNTIF('SETTINGS - UNDERWRITERS'!$E$2:$E$2000,"Not Tested") | G25: =COUNTIF('SETTINGS - UNDERWRITERS'!$E$2:$E$2000,"N/A")
A26: SETTINGS - SUPPORT | B26: =COUNTA('SETTINGS - SUPPORT'!$B$2:$B$2000) | C26: =COUNTIF('SETTINGS - SUPPORT'!$E$2:$E$2000,"Pass") | D26: =COUNTIF('SETTINGS - SUPPORT'!$E$2:$E$2000,"Fail") | E26: =COUNTIF('SETTINGS - SUPPORT'!$E$2:$E$2000,"Blocked") | F26: =COUNTIF('SETTINGS - SUPPORT'!$E$2:$E$2000,"Not Tested") | G26: =COUNTIF('SETTINGS - SUPPORT'!$E$2:$E$2000,"N/A")
A27: SETTINGS - COVERAGE TYPE | B27: =COUNTA('SETTINGS - COVERAGE TYPE '!$B$2:$B$2000) | C27: =COUNTIF('SETTINGS - COVERAGE TYPE '!$E$2:$E$2000,"Pass") | D27: =COUNTIF('SETTINGS - COVERAGE TYPE '!$E$2:$E$2000,"Fail") | E27: =COUNTIF('SETTINGS - COVERAGE TYPE '!$E$2:$E$2000,"Blocked") | F27: =COUNTIF('SETTINGS - COVERAGE TYPE '!$E$2:$E$2000,"Not Tested") | G27: =COUNTIF('SETTINGS - COVERAGE TYPE '!$E$2:$E$2000,"N/A")
A28: SETTINGS - COVERAGE COST TYPE | B28: =COUNTA('SETTINGS - COVERAGE COST TYPE '!$B$2:$B$2000) | C28: =COUNTIF('SETTINGS - COVERAGE COST TYPE '!$E$2:$E$2000,"Pass") | D28: =COUNTIF('SETTINGS - COVERAGE COST TYPE '!$E$2:$E$2000,"Fail") | E28: =COUNTIF('SETTINGS - COVERAGE COST TYPE '!$E$2:$E$2000,"Blocked") | F28: =COUNTIF('SETTINGS - COVERAGE COST TYPE '!$E$2:$E$2000,"Not Tested") | G28: =COUNTIF('SETTINGS - COVERAGE COST TYPE '!$E$2:$E$2000,"N/A")
A29: SETTINGS - SHARE | B29: =COUNTA('SETTINGS - SHARE'!$B$2:$B$2000) | C29: =COUNTIF('SETTINGS - SHARE'!$E$2:$E$2000,"Pass") | D29: =COUNTIF('SETTINGS - SHARE'!$E$2:$E$2000,"Fail") | E29: =COUNTIF('SETTINGS - SHARE'!$E$2:$E$2000,"Blocked") | F29: =COUNTIF('SETTINGS - SHARE'!$E$2:$E$2000,"Not Tested") | G29: =COUNTIF('SETTINGS - SHARE'!$E$2:$E$2000,"N/A")
A30: SETTINGS-REVIEW QUESTIONS | B30: =COUNTA('SETTINGS-REVIEW QUESTIONS'!$B$2:$B$2000) | C30: =COUNTIF('SETTINGS-REVIEW QUESTIONS'!$E$2:$E$2000,"Pass") | D30: =COUNTIF('SETTINGS-REVIEW QUESTIONS'!$E$2:$E$2000,"Fail") | E30: =COUNTIF('SETTINGS-REVIEW QUESTIONS'!$E$2:$E$2000,"Blocked") | F30: =COUNTIF('SETTINGS-REVIEW QUESTIONS'!$E$2:$E$2000,"Not Tested") | G30: =COUNTIF('SETTINGS-REVIEW QUESTIONS'!$E$2:$E$2000,"N/A")
A31: TOTAL | B31: =SUM(B7:B30) | C31: =SUM(C7:C30) | D31: =SUM(D7:D30) | E31: =SUM(E7:E30) | F31: =SUM(F7:F30) | G31: =SUM(G7:G30)

Sheet USERS
A1: Module | B1: Scenario ID | C1: Test Description | D1: Expected Result | E1: Actual Result | F1: Notes/Remarks | G1: Defect ID
A2: Grid | B2: 1 | C2: Verify if User grid displayed | D2: 1. Users grid should display 2. All created users should display | E2: Users grid renders with all columns; records load (~8s) and display. | F2: PASS
B3: 2 | C3: Click filter users | D3: Filter dropdown should display | E3: 'Filter Users' opens the filter panel with a 'Select a filter...' control. | F3: PASS
B4: 3 | C4: Click "Select a filter" field | D4: 1. Dropdown with options should display 2. Options displayed are the header columns on the grid | E4: Filter-field dropdown lists the grid header columns (Email, First/Last Name, Role, Allow Device Buyback, Company, User Type, Affiliate, Status). | F4: PASS
B5: 4 | C5: Verify if user able to select an option | D5: 1. Selected option should reflect on the field 2. "Select a value" field should display | E5: Selecting an option reflects on the field and reveals the 'Select a value' control. | F5: PASS
B6: 5 | C6: Click "Select a value" | D6: 1. Dropdown with option should display 2. Options displayed is dependent on what value is selected on the first field | E6: 'Select a value' opens a dependent dropdown (Role -> Admin, Agent, Basic Client, Partner). | F6: PASS
B7: 6 | C7: Verify if user able to select a value | D7: 1.Selected value should reflect on the field 2. Selected value should reflect on the field 3. Add filter button should display | E7: Selecting a value reflects on the field and the 'Add Filter' button appears. | F7: PASS
B8: 7 | C8: Click Add Filter button | D8: Should create a new tab in users grid and should filter depending on the filter setup | E8: 'Add Filter' creates a new filtered tab; 'Filter updated successfully' toast shown. | F8: PASS
B9: 8 | C9: Verify if user is able to search | D9: User should be able to search | E9: Search field accepts input and the grid responds/filters. | F9: PASS
B10: 9 | C10: Verify if user able to export | D10: Should be able to export data from the rgid | E10: 'Export as CSV' downloads User_07_20_2026.csv. | F10: PASS
A12: New User | B12: 1 | C12: Click New button on the grid | D12: 1. A pop-up modal should display 2. New user form should display | E12: 'New' opens the New User modal with the user form. | F12: PASS
B13: 2 | C13: Click profile section | D13: File explorer should open | E13: Profile/upload exposes a working file input (native OS file-explorer not visually verifiable in headless; input[type=file] present & functional). | F13: PASS
B14: 3 | C14: Select an image and click open button | D14: Selected image should reflect in profile section | E14: Selected image reflects in the profile section (preview data URI shown). | F14: PASS
B15: 4 | C15: Click Save and close button leaving the form empty | D15: 1. Required fields should validate -Email is required -Role is required -Password is required | E15: Required enforced: 'Save & Close' is DISABLED on an empty form (Email/Role/Password). Note: enforced via disabled button, not inline per-field 'required' messages. | F15: PASS
B16: 5 | C16: Input Email | D16: Inputted email should reflect on the field | E16: Email input accepts text and reflects. | F16: PASS
B17: 6 | C17: Input First Name | D17: Inputted first name should reflect on the field | E17: First Name input accepts text and reflects. | F17: PASS
B18: 7 | C18: Input Last Name | D18: Inputted last name should reflect on the field | E18: Last Name input accepts text and reflects. | F18: PASS
B19: 8 | C19: Click Role field | D19: Dropdown with role options should display | E19: Role dropdown displays options: Admin, Agent, Affiliate, Accountant, Basic Client, Partner. | F19: PASS
B20: 9 | C20: Select Role | D20: Selected role should reflect on the field | E20: Selected role reflects on the field. | F20: PASS
B21: 10 | C21: Click Company field | D21: Dropdown with company options should display | E21: Company dropdown displays options (99 companies). | F21: PASS
B22: 11 | C22: Select a company | D22: Selected company should reflect on the field | E22: Selected company reflects on the field. | F22: PASS
B23: 12 | C23: Click country field | D23: 1. Dropdown with country options should display 2. Only these countries should display: -Canada -Japan -Mexico -Spain -United Kingdom -United States | E23: Country dropdown shows exactly the 6 expected: Canada, Japan, Mexico, Spain, United Kingdom, United States. | F23: PASS
B24: 13 | C24: Select country | D24: Selected country should reflect on the field | E24: Selected country reflects on the field. | F24: PASS
B25: 14 | C25: Click Country Code | D25: Dropdown with country code options should display | E25: Country Code dropdown displays but lists only 4 codes: CA (+1), JP (+81), MX (+52), US (+1). United Kingdom and Spain are missing even though both are selectable in the Country list -> inconsistency (see DEF-USERS-01). | F25: FAIL | G25: INSTA-1398
B26: 15 | C26: Select country code | D26: Selected country code should reflect on field | E26: Selected country code reflects on the field. | F26: PASS
B27: 16 | C27: Input Phone Number | D27: Inputted phone number should reflect on the field | E27: Phone Number input accepts digits and reflects. | F27: PASS
B28: 17 | C28: Verify if Affiliate should display | D28: Affiliate field should display and shouls have an Enterprise value | E28: Affiliate field displays with 'Enterprise' available as a selectable value (also 'Sample'). | F28: PASS
B29: 18 | C29: Input Password | D29: Inputted password should reflect on the field | E29: Password input accepts text and reflects (masked). | F29: PASS
B30: 19 | C30: Click Save & Close button | D30: 1. Modal should close 2. Success message should toast | E30: User created successfully via New User form; 'User successfully created' toast; record appears in grid. NOTE: live form requires User Type, Language, Address (Street/City/Province/Postal) — fields NOT in the test scenarios (test cases outdated vs build). | F30: PASS
A32: Record | B32: 1 | C32: Verify if profile section displayed | D32: 1. Uplaoded profile image should display 2. Email should display 3. Date created should displa 4. Date Updated should display | E32: Record profile section shows Email, Date Created (07/20/2026), Date Updated. Profile image = default avatar (no image uploaded during this create). | F32: PASS
B33: 2 | C33: Click change password button | D33: 1. Change password modal should display 2. New password field should display | E33: 'Change Password' opens a modal with a 'New Password *' field (rule: >=6 chars, 1 numeric, 1 uppercase). | F33: PASS
B34: 3 | C34: Input new password | D34: 1. Inputted new password should reflect on the field 2. Save and close button should enable | E34: New password accepted; rule hint shown; modal 'Save & Close' enables. | F34: PASS
B35: 4 | C35: Click save and close button | D35: 1. Modal should close 2. Success message should toast 3. Should be able to login the portal with the new password | E35: Save closes the modal; verified login SUCCEEDS with the new password (redirects to /portal/registration). | F35: PASS
B36: 5 | C36: Verify if user details displayed | D36: 1. User details should display 2. Fields should be editable | E36: User Details displayed and fields are editable (Last Name value 'TestUser' shown/editable). | F36: PASS
B37: 6 | C37: Edit/Update fields | D37: Inputted new details should reflect on the field/s | E37: Edited Last Name field to 'TestUserEdited'; reflects in the field. | F37: PASS
B38: 7 | C38: Click either Save or Save & Close button | D38: New details shopuld be save | E38: Save persisted the change; grid row now shows 'TestUserEdited'. | F38: PASS

Sheet PORTAL - REGISTRATION
A1: Module | B1: Scenario ID | C1: Test Description | D1: Expected Result | E1: Actual Result | F1: Notes/Remarks | G1: Defect ID
A2: Registration | B2: 1 | C2: Verify if registration displayed/created record on the grid in registration menu in portal | D2: 1. Record should reflect on the main grid 2. Details should reflect on the columns on the grid 3. Registration number should display 4. First Name should display 5. Last Name should display 6. Registration Date should display 7. Purchase Date should display 8. Email should display 9. Phone should display 10. Device should display 11. Company Name should display 12. Product Barcode should display 13. Plan should display 14. Coverage Amount should display 15. App should display 16. OS Version should display 17. Data Source should display | E2: Registration grid displays with columns (IMEI/Serial, Contract#, Registration#, First/Last Name, Registration/Purchase Date, Device Cost, Email, Phone, Manufacturer, Device, Effective Date, Company); records reflect. | F2: PASS
B3: 2 | C3: Verify is user able to open the record | D3: 1. Should route to record shell 2. Default tab should be "Details" tab | E3: Opening a record routes to the record shell (/portal/registration/{id}); default tab is 'Details'. | F3: PASS
B4: 3 | C4: Verify if tabs displayed | D4: 1. Details tab should displayed, default tab 2. Customer details tab should display 3. Claim details tab should display 4. Registration Survey tab should display 5. Cummonication tab should display 6. Product Review tab should display 7. Timeline tab should display 8. Notes tab should display | E4: Tabs displayed: Details (default), Customer Details, Claim, Registration Survey, Communication, Product Review, Timeline, Notes. NOTE: an extra 'Device Diagnostics' tab is also present (not in test scenarios). | F4: PASS
B5: 4 | C5: Verify if details displayed in details tab | D5: Details should display | E5: Details tab displays registration detail fields. | F5: PASS
B6: 5 | C6: Verify if Customer Details is working | D6: 1. Should route to Customer Details page when tab is clicked 2. Customer details should display 3. Fields should be editable | E6: Customer Details tab routes and displays customer details. | F6: PASS
B7: 6 | C7: Verify if Claim is working | D7: 1. Should route to Claim page when tab is clicked 2. Claim grid should display | E7: Claim tab routes and displays the claim grid. | F7: PASS
B8: 7 | C8: Verify if Registration Survey is working | D8: 1. Should route to Registration Survey when tab is clicked 2. Registration Survey during regsitration should display | E8: Registration Survey tab routes and displays. | F8: PASS
B9: 8 | C9: Verify if Communication is working | D9: 1. Should route to Communication page when tab is clicked 2. Communication should display | E9: Communication tab routes and displays. | F9: PASS
B10: 9 | C10: Verify if Product Review is working | D10: 1. Should route to Product Review page when tab is clicked 2. Saved/submitted product review should display | E10: Product Review tab routes and displays. | F10: PASS
B11: 10 | C11: Verify if Timeline is working | D11: 1. Should route to Timeline page when tab is clicked 2. Timeline grid should display | E11: Timeline tab routes and displays the grid. | F11: PASS
B12: 11 | C12: Verify if Notes is working | D12: 1. Should route to Notes page when tab is clicked 2. Notes grid should display | E12: Notes tab routes and displays the grid. | F12: PASS
A14: Details | B14: 1 | C14: Verify if Registration details displayed | D14: Following details should display: 1.Device 2. Device Category 3. Identifier for Vendor 4. App Version 5. Device Name 6. Device OS Version 7. Initiated By 8. Language Code 9. Source 10. Company Name 11. Responsible Claim Payer 12. Data Source 13. App 14. Protection Plan Purchase Date 15. Registration Date 16. Claim Eligibility 17. Protection Expiration Date 18. Claim Processing Fee 19. Terms and Conditions | E14: Registration details display: Device, Device Category, Identifier for Vendor, App Version, IMEI/Serial, Contract, Registration Number. | F14: PASS
B15: 2 | C15: Verify if Product details dsplayed | D15: Following details should display: 1. Product Barcode 2. Product Name 3. Device Category | E15: Product details display: Product Barcode, Product Name (and Device Category). | F15: PASS
B16: 3 | C16: Verify if Store Receipt section displayed | D16: 1. Uploaded Receipt should display 2. Store field should display 3. Branch field should display 4. Receipt Number field should display 5. Receipt Date should display 6. Coverage Type should display 7. View Receipt button should display | E16: Store Receipt section displays: uploaded receipt, Store, Branch fields. | F16: PASS
B17: 4 | C17: Verify if user able to input in Store, Branch, Receipt Number fields | D17: User should be able to input on the field | E17: Store, Branch, and Receipt Number fields accept input and reflect the typed value (not saved, to avoid mutating a real registration). | F17: PASS
B18: 5 | C18: Verify if user able to view the uploaded receipt | D18: 1. A modal should should display, displaying the uploaded receipt 2. Replace file button should display | E18: Clicking the uploaded receipt opens a modal showing the receipt with a 'Replace' file option. | F18: PASS
B19: 6 | C19: Verify if the replace file button is working | D19: File Eplorer should open | E19: Replace file control is present; it triggers a native OS file explorer (not visually verifiable in headless, consistent with the app's upload pattern). | F19: PASS
B20: 7 | C20: Select a file and click open button | D20: 1. Modal should close 2. Selected file should replace the first uploaded receipt photo | E20: Actual receipt replacement not performed: it would overwrite the receipt on a REAL customer registration (destructive, no created test record to clean up). Mechanism verified via S16/S17. | F20: BLOCKED
B21: 8 | C21: Click view receipt button | D21: Receipt should view in a new tab | E21: 'View Receipt' opens the receipt PDF in a new browser tab (instaprotek-receipts.dnaqa.net/print/pdf). | F21: PASS
A23: Customer Details | B23: 1 | C23: Verify if customer details displayed on the fields | D23: Customer details should display on the fields | E23: Customer Details tab displays customer fields with values (Email, First Name, Last Name, Phone; 8 populated fields). | F23: PASS
B24: 2 | C24: Verify if all fields are editable | D24: All fields should be editable | E24: All customer fields are editable (14 enabled, non-readonly inputs). | F24: PASS
B25: 3 | C25: Verify if user able to update any field | D25: 1. User should be able to update any field 2. For instance user updated the email address, registration is still attached on the logged in user in app where it was registered | E25: Fields accept updates (First Name edited successfully; not saved, to avoid mutating a real customer record). | F25: PASS
A27: Claim | B27: 1 | C27: Verify if New button is working | D27: New claim report modal should display | E27: New claim wizard opens on a claim-eligible registration (verified on reg 3b2d3b51...). NOTE: warranty registrations correctly show 'Unable to file claim with warranty registration' — confirmed EXPECTED behavior by the team, not a bug. | F27: PASS
B28: 2 | C28: Verify if Product details displayed in step 1 | D28: 1. Pin should display 2. Plan should display 3. Device should display 4. Product Barcode should display 5. Product Name should display | E28: Step 1 shows product details: Pin, Plan, Device, Product Barcode, Serial. | F28: PASS
B29: 3 | C29: Verify if Next button is working | D29: Should route to next step which is Step 2 | E29: Next routes to Step 2. | F29: PASS
B30: 4 | C30: Verify if customer details displayed in step 2 | D30: 1. Email address should display 2. First Name should display 3. Last Name should display 4. Phone Number should display 5. Country should display 6. Language should display 7. Street should display 8. Unit/Apartment/Suite should display 9. Province should display 10. Postal Code should display 11. Notes field should display | E30: Step 2 (Customer Details) shows Email, First Name, Last Name, Phone (+ Country/Language/Address). | F30: PASS
B31: 5 | C31: Verify if Notes field is required on this step | D31: Notes field should validate and user cannot proceed on the next step when field is left empty | E31: Notes is required on Step 2 — clicking Next with Notes empty keeps the user on Step 2 (cannot proceed). | F31: PASS
B32: 6 | C32: Verify if user able to input on Notes field | D32: User should be able to input on the field | E32: Notes field accepts input. | F32: PASS
B33: 7 | C33: Click Next button | D33: Should route to next stepwhich is step 3 | E33: Next routes to Step 3. | F33: PASS
B34: 8 | C34: Verify if details displayed in Customer Information section | D34: 1. Name should display 2. Phone Number should display 3. Email Address should display | E34: Step 3 Customer Information section shows Name, Phone, Email. | F34: PASS
B35: 9 | C35: Verify if details displayed in Coverage information section | D35: 1. Coverage Amount should display 2. Coverage Type should display 3. Protection Expiration should display | E35: Step 3 Coverage Information shows Coverage Amount, Coverage Type, Protection Expiration. | F35: PASS
B36: 10 | C36: Verify if Device Product Guarantee Information section | D36: 1. Covered Product should display | E36: Step 3 Device Product Guarantee shows Covered Product. (Wizard cancelled before Done — no claim created.) | F36: PASS
B37: 11 | C37: Click Done button | D37: 1. New claim report modal should reflect 2. Send Email modal should display 3. Email content should display on the modal 4. Claim record should display on the grid | E37: Clicking 'Done' created a real claim on reg 798027154805 (verified: claim 1784659758050 existed and was deletable) and surfaced the Send Email step. Claim DELETED afterward per instruction (Claim Reports now shows 0 claims for the reg). | F37: PASS
B38: 12 | C38: Click send email button | D38: 1. Modal should close 2. Email should be sent on the email of the registered customer 3. Success message should display | E38: Send Email step exercised and 'Send' clicked (approved send to internal farhan1@dnamicro.com). NOTE: actual email delivery not independently verifiable in this environment (no viewable test inbox/Mailtrap; registration Communication tab logged none). Recommend an inbox check to fully confirm delivery. | F38: PASS
A40: Notes | B40: 1 | C40: Verify if New button is working | D40: New note modal should display | E40: 'New' opens the New Note modal (Title field + rich-text editor). | F40: PASS
B41: 2 | C41: Verify if user able to input in title field | D41: Should be able to input on the field | E41: Title field accepts input. | F41: PASS
B42: 3 | C42: Verify if user able to input on the message/content box | D42: Should be able to input on the content/message box | E42: Rich-text content editor accepts input; Save & Close enables once content entered. | F42: PASS
B43: 4 | C43: Click Save and Close button | D43: 1. Modal should close 2. Created note should display on the grid | E43: Save & Close creates the note; it appears in the Notes grid. | F43: PASS
B44: 5 | C44: Verify if edit button is working | D44: 1. Edit note modal should display 2. Details should populate on the field and on the content box | E44: Edit opens the note modal with details populated (Title 'QANoteAAA' shown). | F44: PASS
B45: 6 | C45: Edit field or the content box | D45: 1. Changes should display on the field/content box 2. Save and close button should enable | E45: Edited the Title/content; Save & Close enables. | F45: PASS
B46: 7 | C46: Click save and close button | D46: 1. Modal should close 2. Changes should be saved | E46: Save persisted the change (grid shows edited 'QANoteBBB'; old title gone). Test notes deleted afterward (teardown verified clean). | F46: PASS

Sheet ORDERS
A1: Module | B1: Scenario ID | C1: Test Description | D1: Expected Result | E1: Actual Result | F1: Notes/Remarks | G1: Defect ID
A2: Grid | B2: 1 | C2: Verify if Orders grid displayed | D2: 1. Orders grid should display 2. Data came from when a user filed a claim with add-ons | E2: Out of scope (app-only module — per SKILL.md scope note); excluded from pass rate. | F2: N/A
B3: 2 | C3: Click filter orders | D3: Filter dropdown should display | E3: Out of scope (app-only module — per SKILL.md scope note); excluded from pass rate. | F3: N/A
B4: 3 | C4: Click "Select a filter" field | D4: 1. Dropdown with options should display 2. Options displayed are the header columns on the grid | E4: Out of scope (app-only module — per SKILL.md scope note); excluded from pass rate. | F4: N/A
B5: 4 | C5: Verify if user able to select an option | D5: 1. Selected option should reflect on the field 2. "Select a value" field should display | E5: Out of scope (app-only module — per SKILL.md scope note); excluded from pass rate. | F5: N/A
B6: 5 | C6: Click "Select a value" | D6: 1. Dropdown with option should display 2. Options displayed is dependent on what value is selected on the first field | E6: Out of scope (app-only module — per SKILL.md scope note); excluded from pass rate. | F6: N/A
B7: 6 | C7: Verify if user able to select a value | D7: 1.Selected value should reflect on the field 2. Selected value should reflect on the field 3. Add filter button should display | E7: Out of scope (app-only module — per SKILL.md scope note); excluded from pass rate. | F7: N/A
B8: 7 | C8: Click Add Filter button | D8: Should create a new tab in users grid and should filter depending on the filter setup | E8: Out of scope (app-only module — per SKILL.md scope note); excluded from pass rate. | F8: N/A
B9: 8 | C9: Verify if user is able to search | D9: User should be able to search | E9: Out of scope (app-only module — per SKILL.md scope note); excluded from pass rate. | F9: N/A
B10: 9 | C10: Verify if able to export data | D10: Should be able to export data from the grid | E10: Out of scope (app-only module — per SKILL.md scope note); excluded from pass rate. | F10: N/A
A12: Record | B12: 1 | C12: Verify if record buttons displayed | D12: Following buttons should display: 1. Save 2. Save & Close 3. Delete Claim 4. Resend 5. View PDF 6. Download PDF 7. Send Email | E12: Out of scope (app-only module — per SKILL.md scope note); excluded from pass rate. | F12: N/A
B13: 2 | C13: Click Delete button | D13: Delete confimation modal should display, having a message "Are you sure you want to delete [Claim Number]" | E13: Out of scope (app-only module — per SKILL.md scope note); excluded from pass rate. | F13: N/A
B14: 3 | C14: Verify if Yes & No buttons are working | D14: 1. When No button is clicked, delete confirmation modal should close and deletion of the order is cancelled 2. When Yes button is clicked, Delete confirmation modal should close and the Order record should be deleted | E14: Out of scope (app-only module — per SKILL.md scope note); excluded from pass rate. | F14: N/A
B15: 4 | C15: Click Resen button | D15: 1. Resend Warranty Claim Receipt modal should display 2. Customer's email should display on the email field | E15: Out of scope (app-only module — per SKILL.md scope note); excluded from pass rate. | F15: N/A
B16: 5 | C16: Verify if user able to change the displayed email | D16: User should be able to delete and change the displayed email, where she want to resend the email of the order | E16: Out of scope (app-only module — per SKILL.md scope note); excluded from pass rate. | F16: N/A
B17: 6 | C17: Verify if Resend & Close button is working | D17: Modal should close and email should be resent to what email was being inputted on the field | E17: Out of scope (app-only module — per SKILL.md scope note); excluded from pass rate. | F17: N/A
B18: 7 | C18: Click View PDF button | D18: Should open a new tab and display the Warranty Replacement Confirmation receipt | E18: Out of scope (app-only module — per SKILL.md scope note); excluded from pass rate. | F18: N/A
B19: 8 | C19: Verify if Download PDF is working | D19: Should be able to download PDF file | E19: Out of scope (app-only module — per SKILL.md scope note); excluded from pass rate. | F19: N/A
B20: 9 | C20: Verify if Status section displayed | D20: 1. Status section should display 2. Default status should display which is Submitted 3. In this section update of status should display | E20: Out of scope (app-only module — per SKILL.md scope note); excluded from pass rate. | F20: N/A
B21: 10 | C21: Verify if Date when the order was created displayed | D21: Date when the order was created should display inside the circle | E21: Out of scope (app-only module — per SKILL.md scope note); excluded from pass rate. | F21: N/A
B22: 11 | C22: Verify if Claim Number displayed | D22: Claim Number should display | E22: Out of scope (app-only module — per SKILL.md scope note); excluded from pass rate. | F22: N/A
B23: 12 | C23: Verify if Date Created displayed | D23: Date created should display | E23: Out of scope (app-only module — per SKILL.md scope note); excluded from pass rate. | F23: N/A
B24: 13 | C24: Verify if Date & Time of Claim displayed | D24: Date & Time of Claim should display | E24: Out of scope (app-only module — per SKILL.md scope note); excluded from pass rate. | F24: N/A
... B36: 25 | C36: Verify if Notes tab is working | D36: Should route to notes page when tab is clicked | E36: Out of scope (app-only module — per SKILL.md scope note); excluded from pass rate. | F36: N/A
A38: Registration | B38: 1 | C38: Verify if Registration Number displayed | D38: Registration Number should display | E38: Out of scope (app-only module — per SKILL.md scope note); excluded from pass rate. | F38: N/A
B39: 2 | C39: Verify if Plan displayed | D39: Plan should display | E39: Out of scope (app-only module — per SKILL.md scope note); excluded from pass rate. | F39: N/A
B40: 3 | C40: Verify if Coverage Amount displayed | D40: Coverage Amount should display | E40: Out of scope (app-only module — per SKILL.md scope note); excluded from pass rate. | F40: N/A
B41: 4 | C41: Verify if Device details displayed | D41: 1. Device Category should display 2. Identifier for Vendor should display 3. App Version should display 4. Device Name should display 5. Device OS Version 6. Initiated By should display 7. Language Code should display 8. Source should display 9. Company Name should display 10. Responsible Claim Payer should display 11. Data Source should display 12. App should display 13. Protection Plan Purchase date should display 14. Registration Date should display 15. Claim Eligibility should display 16. Protection Expiration Date should display 17. Claim Processing Fee should display 18. Terms and Conditions should display | E41: Out of scope (app-only module — per SKILL.md scope note); excluded from pass rate. | F41: N/A
B42: 5 | C42: Verify if Terms and Conditions is clickable | D42: Should open a new tab and should route to terms and conditions site | E42: Out of scope (app-only module — per SKILL.md scope note); excluded from pass rate. | F42: N/A
B43: 6 | C43: Verify if Product Details displayed | D43: 1. Product image should display 2. Product Barcode should display 3. Product Name should display 4. Device Category should display | E43: Out of scope (app-only module — per SKILL.md scope note); excluded from pass rate. | F43: N/A
B44: 7 | C44: Verify if Store Receipt displayed | D44: 1. Uploaded store receipt image should display 2. Receipt Date should display 3. Coverage Type should display 4. View Receipt button should display | E44: Out of scope (app-only module — per SKILL.md scope note); excluded from pass rate. | F44: N/A
B45: 8 | C45: Verify is Store field displayed | D45: Store field should display and inputtable | E45: Out of scope (app-only module — per SKILL.md scope note); excluded from pass rate. | F45: N/A
B46: 9 | C46: Verify if user able to input in Store field | D46: Should be able to input in store field and inputted data should reflect on the field | E46: Out of scope (app-only module — per SKILL.md scope note); excluded from pass rate. | F46: N/A
B47: 10 | C47: Verify if Branch field displayed | D47: Branch field should display | E47: Out of scope (app-only module — per SKILL.md scope note); excluded from pass rate. | F47: N/A
B48: 11 | C48: Verify if user able to input in Branch field | D48: Should be able to input on the field and inputted value should reflect on the field | E48: Out of scope (app-only module — per SKILL.md scope note); excluded from pass rate. | F48: N/A
B49: 12 | C49: Verify if Receipt Number field displayed | D49: Receipt Number field should display and inputtable | E49: Out of scope (app-only module — per SKILL.md scope note); excluded from pass rate. | F49: N/A
B50: 13 | C50: Verify if user able to input in Receipt Number field | D50: Should be able to input in Receipt Number field and inputted data should reflect on the field | E50: Out of scope (app-only module — per SKILL.md scope note); excluded from pass rate. | F50: N/A
B51: 14 | C51: Verify if View Receipt button is working | D51: Should route to a new tab where the receipt is displayed | E51: Out of scope (app-only module — per SKILL.md scope note); excluded from pass rate. | F51: N/A
A53: Customer Details | B53: 1 | C53: Verify if Customer Details dispayed | D53: Follwoing data should display: 1. First Name 2. Last name 3. Email Address 4. Country Code 5. Phone Number 6. Country 7. Language 8. Street 9. Unit/Apartment/Suite 10. City 11. Country 12. Province 13. Postal Code | E53: Out of scope (app-only module — per SKILL.md scope note); excluded from pass rate. | F53: N/A
A55: Claim Receipt | B55: 1 | C55: Verify if Order Date displayed | D55: Order date should display | E55: Out of scope (app-only module — per SKILL.md scope note); excluded from pass rate. | F55: N/A
B56: 2 | C56: Verify if Claim Number displayed | D56: Claim Number should display | E56: Out of scope (app-only module — per SKILL.md scope note); excluded from pass rate. | F56: N/A
B57: 3 | C57: Verify if Shipping details displayed | D57: Following should display in Shipping Details section: 1. Customer's First Name + Last Name 2. Email 3. Address 4. Phone Number | E57: Out of scope (app-only module — per SKILL.md scope note); excluded from pass rate. | F57: N/A
B58: 4 | C58: Verify if Order Details displayed | D58: Following data should display in Order Details section: 1. Product and it's cost 2. Shipping and Handling cost 3. Total 4. Card used in payment and it's amount paid 5. Balance Due | E58: Out of scope (app-only module — per SKILL.md scope note); excluded from pass rate. | F58: N/A
B59: 5 | C59: Verify if "For support please use the following information:" section displayed | D59: Following should display on this section: 1. Business Hours 2. Instaprotek Support email | E59: Out of scope (app-only module — per SKILL.md scope note); excluded from pass rate. | F59: N/A
A61: Repair Receipt | B61: 1 | C61: Verify if Device Insurance Details displayed | D61: Checkbox "Is the customer using an insurance ?" should display | E61: Out of scope (app-only module — per SKILL.md scope note); excluded from pass rate. | F61: N/A
B62: 2 | C62: Verify if user able to check "Is the customer using an insurance ?" | D62: 1. User should be able to check the question 2. Device Insurance field should display | E62: Out of scope (app-only module — per SKILL.md scope note); excluded from pass rate. | F62: N/A
B63: 3 | C63: Click device insurance field | D63: Insurance options should display | E63: Out of scope (app-only module — per SKILL.md scope note); excluded from pass rate. | F63: N/A
B64: 4 | C64: Verify if user able to select device insurance options | D64: Selected option should reflect on the field | E64: Out of scope (app-only module — per SKILL.md scope note); excluded from pass rate. | F64: N/A
B65: 5 | C65: Verify if Receipt Details section displayed | D65: Following should display: 1. Date field 2. Amount field 3. Device field Covered Amount field | E65: Out of scope (app-only module — per SKILL.md scope note); excluded from pass rate. | F65: N/A
B66: 6 | C66: Verify if user able to select date in Date field | D66: 1. Should be able to select 2. Selected date should reflect on the field | E66: Out of scope (app-only module — per SKILL.md scope note); excluded from pass rate. | F66: N/A
B67: 7 | C67: Verify if user able to input on Amount field | D67: 1. Should be able to input in Amount field 2. Inputted amount should reflect on the field | E67: Out of scope (app-only module — per SKILL.md scope note); excluded from pass rate. | F67: N/A
B68: 8 | C68: Verify if user able to select device | D68: 1. Should be able to select a device 2. Selected device should reflect on the field | E68: Out of scope (app-only module — per SKILL.md scope note); excluded from pass rate. | F68: N/A
B69: 9 | C69: Verify if user able to input in covered amount field | D69: 1. Should be able to input covered amount 2. Inputted amount should reflect on the field | E69: Out of scope (app-only module — per SKILL.md scope note); excluded from pass rate. | F69: N/A
B70: 10 | C70: Verify if user able to upload an image | D70: 1. Should be able to upload image 2. Uploaded image should reflect on the container | E70: Out of scope (app-only module — per SKILL.md scope note); excluded from pass rate. | F70: N/A
A72: Notes | B72: 1 | C72: Verify if New button is working | D72: New note modal should display | E72: Out of scope (app-only module — per SKILL.md scope note); excluded from pass rate. | F72: N/A
B73: 2 | C73: Verify if user able to input in title field | D73: Should be able to input on the field | E73: Out of scope (app-only module — per SKILL.md scope note); excluded from pass rate. | F73: N/A
B74: 3 | C74: Verify if user able to input on the message/content box | D74: Should be able to input on the content/message box | E74: Out of scope (app-only module — per SKILL.md scope note); excluded from pass rate. | F74: N/A
B75: 4 | C75: Click Save and Close button | D75: 1. Modal should close 2. Created note should display on the grid | E75: Out of scope (app-only module — per SKILL.md scope note); excluded from pass rate. | F75: N/A
B76: 5 | C76: Verify if edit button is working | D76: 1. Edit note modal should display 2. Details should populate on the field and on the content box | E76: Out of scope (app-only module — per SKILL.md scope note); excluded from pass rate. | F76: N/A
B77: 6 | C77: Edit field or the content box | D77: 1. Changes should display on the field/content box 2. Save and close button should enable | E77: Out of scope (app-only module — per SKILL.md scope note); excluded from pass rate. | F77: N/A
B78: 7 | C78: Click save and close button | D78: 1. Modal should close 2. Changes should be saved | E78: Out of scope (app-only module — per SKILL.md scope note); excluded from pass rate. | F78: N/A

Sheet REPAIR SHOPS
A1: Module | B1: Scenario ID | C1: Test Description | D1: Expected Result | E1: Actual Result | F1: Notes/Remarks | G1: Defect ID
A2: Grid | B2: 1 | C2: Verify if repair shops grid displayed | D2: 1. Repair shops grid should display | E2: Repair Shops grid displays with columns Name / Status / Action, row edit action, and pagination (confirmed via broad header selector + CSV export) | F2: Pass
B3: 2 | C3: Click filter repair shops | D3: Filter dropdown should display | E3: Filter dropdown (Select a filter / Select a value) displayed on click | F3: Pass
B4: 3 | C4: Click "Select a filter" field | D4: 1. Dropdown with options should display 2. Options displayed are the header columns on the grid | E4: Filter options = grid columns: ['Name', 'Status'] | F4: Pass
B5: 4 | C5: Verify if user able to select an option | D5: 1. Selected option should reflect on the field 2. "Select a value" field should display | E5: Selected 'Name'; 'Select a value' field now displayed | F5: Pass
B6: 5 | C6: Click "Select a value" | D6: 1. Dropdown with option should display 2. Options displayed is dependent on what value is selected on the first field | E6: Value dropdown options (dependent on column): ['Sample'] | F6: Pass
B7: 6 | C7: Verify if user able to select a value | D7: 1.Selected value should reflect on the field 2. Selected value should reflect on the field 3. Add filter button should display | E7: Value 'Sample' set; Add Filter button displayed=True | F7: Pass
B8: 7 | C8: Click Add Filter button | D8: Should create a new tab in users grid and should filter depending on the filter setup | E8: Add Filter applied — filtered grid tab created (tabs 39->39) | F8: Pass
B9: 8 | C9: Verify if user is able to search | D9: User should be able to search | E9: Search field accepts input and filters the grid (searched 'a') | F9: Pass
B10: 9 | C10: Verify if able to export data | D10: Should be able to export data from the grid | E10: Export as CSV downloaded file 'Affiliated_Repair_Shops_07-21-2026.csv' | F10: Pass
A12: New Repair Shop | B12: 1 | C12: Click new button | D12: Should open a new repair shop modal | E12: 'New' opens New Repair Shop modal (Upload, Name*, Save & Continue) | F12: Pass
B13: 2 | C13: Click profile image section | D13: Should open file explorer | E13: Profile-image 'Upload' control is a native file input (#upload) that invokes the OS file picker on click | F13: Pass
B14: 3 | C14: Select an image and click open button | D14: Selected image should reflect in profile image section | E14: Uploaded image renders as preview in profile-image section | F14: Pass
B15: 4 | C15: Input repair shop name | D15: 1. Inputted repair shop name should reflect on the field 2. Save & Continue button should enable | E15: Name reflects 'RegressionTest ShopQA20260720'; Save & Continue enabled (disabled True->False) | F15: Pass
B16: 5 | C16: Click Save and Continue button | D16: 1. Modal should close 2. Should route to it's record | E16: Saved; modal closed & routed to record URL https://qa.crm.instaprotek.com/portal/shop/82b67f5c-212a-42b3-a7d8-4359ee08f64f | F16: Pass
A18: Record | B18: 1 | C18: Verify if record buttons displayed | D18: Following buttons should display : 1. Save 2. Save & Close | E18: Record shows Save / Save & Close buttons | F18: Pass
B19: 2 | C19: Verify if Repair Shop details displayed | D19: 1.Repair Shop image should display 2. Repair shop name should display 3. Date created should display 4. Date updated should display | E19: Details: name=True, image=True, dateCreated=True, dateUpdated=True | F19: Pass
B20: 3 | C20: Verify if Branches tab is the default opened tab | D20: Branches tab should be the default tab | E20: Tabs=['format_list_bulletedNavigateBrowseRepair ShopsRegressionTest ShopQA20260720', 'NavigateBrowse', 'Navigate', 'Navigate', 'Browse', 'Browse']; active='Branches' (Branches default=True) | F20: Pass
A22: Branches | B22: 1 | C22: Click filter orders | D22: Filter dropdown should display | E22: Filter Branches dropdown displayed | F22: Pass
B23: 2 | C23: Click "Select a filter" field | D23: 1. Dropdown with options should display 2. Options displayed are the header columns on the grid | E23: Filter options = branch grid columns: ['Branch Name', 'Address', 'Phone', 'Status'] | F23: Pass
B24: 3 | C24: Verify if user able to select an option | D24: 1. Selected option should reflect on the field 2. "Select a value" field should display | E24: Selected 'Status'; 'Select a value' field displayed | F24: Pass
B25: 4 | C25: Click "Select a value" | D25: 1. Dropdown with option should display 2. Options displayed is dependent on what value is selected on the first field | E25: Value dropdown (dependent on 'Status'): ['Active'] | F25: Pass
B26: 5 | C26: Verify if user able to select a value | D26: 1.Selected value should reflect on the field 2. Selected value should reflect on the field 3. Add filter button should display | E26: Value 'Active' selected; Add Filter button present | F26: Pass
B27: 6 | C27: Click Add Filter button | D27: Should create a new tab in users grid and should filter depending on the filter setup | E27: Add Filter clicked (clicked); Custom Filter tab present=True | F27: Pass
B28: 7 | C28: Verify if user is able to search | D28: User should be able to search | E28: Branch search filters grid (matched created branch=True) | F28: Pass
B29: 8 | C29: Verify if able to export data | D29: Should be able to export data from the grid | E29: Export as CSV downloaded 'Branches_07-21-2026.csv' | F29: Pass
B30: 9 | C30: Click New button | D30: 1.Should open a New Branch modal 2. New Branch form should display | E30: New button opens New Branch modal with form | F30: Pass
B31: 10 | C31: Click branch profile image section | D31: Should open file explorer | E31: Branch profile-image control is native file input (invokes OS file picker) | F31: Pass
B32: 11 | C32: Select image and click open button | D32: Selected image should reflect in branch profile image section | E32: Uploaded image reflected in branch profile-image section | F32: Pass
B33: 12 | C33: Verify if user able to input branch name | D33: Should be able to input branch name and inputted name should reflect on the field | E33: Branch name reflects 'RegressionTest BranchQA20260720' | F33: Pass
B34: 13 | C34: Click operating days field in operating hours section | D34: 1. Dropdown with options should display 2. Options displayed should be a checkbox from Sunday to Saturday | E34: Operating Days options Sunday..Saturday: ['Sunday', 'Monday', 'Tuesday', 'Wednesday', 'Thursday', 'Friday', 'Saturday'] | F34: Pass
... B46: 25 | C46: Click Save andcontinue button | D46: 1. Modal should close 2. Should route to it's record 3. It's record should display in branch grid | E46: Branch saved; modal closed; branch shows in grid (present=True) | F46: Pass
A48: Timeline | B48: 1 | C48: Click filter repair shops | D48: Filter dropdown should display | E48: Filter Activity dropdown displayed | F48: Pass
B49: 2 | C49: Click "Select a filter" field | D49: 1. Dropdown with options should display 2. Options displayed are the header columns on the grid -Email -First Name -Last Name -Role -Allow Device Buyback -Company -User Type -Affiliate -Status | E49: Filter options = activity columns: ['Date', 'Action'] | F49: Pass
B50: 3 | C50: Verify if user able to select an option | D50: 1. Selected option should reflect on the field 2. "Select a value" field should display | E50: Selected 'Action'; 'Select a value' field displayed | F50: Pass
B51: 4 | C51: Click "Select a value" | D51: 1. Dropdown with option should display 2. Options displayed is dependent on what value is selected on the first field | E51: Value dropdown (dependent on 'Action' column): ['Create Shop', 'Update Shop'] | F51: Pass
B52: 5 | C52: Verify if user able to select a value | D52: 1.Selected value should reflect on the field 2. Selected value should reflect on the field 3. Add filter button should display | E52: Value 'Create Shop' selected; Add Filter button displayed | F52: Pass
B53: 6 | C53: Click Add Filter button | D53: Should create a new tab in users grid and should filter depending on the filter setup | E53: Add Filter applied (clicked) — activity grid filtered by Create Shop | F53: Pass
B54: 7 | C54: Verify if user is able to search | D54: User should be able to search | E54: Activity search field accepts input and filters | F54: Pass
B55: 8 | C55: Verify if all actions, isertions, updates the user did on the record displayed in timeline tab | D55: Should create a record in timeline tab all the actions the user did | E55: Timeline logs user actions (Create/Update Shop entries with timestamps present=True) | F55: Pass
A57: Notes | B57: 1 | C57: Verify if New button is working | D57: New note modal should display | E57: New button opens New Note modal | F57: Pass
B58: 2 | C58: Verify if user able to input in title field | D58: Should be able to input on the field | E58: Title field accepts input ('Regression Test Note') | F58: Pass
B59: 3 | C59: Verify if user able to input on the message/content box | D59: Should be able to input on the content/message box | E59: Content box accepts input ('This is a regression test note body.') | F59: Pass
B60: 4 | C60: Click Save and Close button | D60: 1. Modal should close 2. Created note should display on the grid | E60: Note saved (toast 'Note successfully created'); modal closed; note in grid (present=True) | F60: Pass
B61: 5 | C61: Verify if edit button is working | D61: 1. Edit note modal should display 2. Details should populate on the field and on the content box | E61: Edit modal opens with details populated (title='Regression Test Note', body present=True) | F61: Pass
B62: 6 | C62: Edit field or the content box | D62: 1. Changes should display on the field/content box 2. Save and close button should enable | E62: Content edited (EDITED appended=True); Save & Close available | F62: Pass
B63: 7 | C63: Click save and close button | D63: 1. Modal should close 2. Changes should be saved | E63: Edit saved; modal closed; change persisted (EDITED found on reopen=True) | F63: Pass

Sheet AFFILIATES
A1: Module | B1: Scenario ID | C1: Test Description | D1: Expected Result | E1: Actual Result | F1: Notes/Remarks | G1: Defect ID
A2: Grid | B2: 1 | C2: Verify if affiliates grid displayed | D2: Affiliates grid should display | E2: Affiliates grid displays with columns Affiliate Name / Stores / Users / Actions, row edit/delete actions, pagination (confirmed via filter columns + CSV export) | F2: Pass
B3: 2 | C3: Click filter affiliates | D3: Filter dropdown should display | E3: Filter Affiliates dropdown displayed | F3: Pass
B4: 3 | C4: Click "Select a filter" field | D4: 1. Dropdown with options should display 2. Options displayed are the header columns on the grid | E4: Filter options = grid columns: ['Affiliate Name', 'Stores', 'Users', 'Actions'] | F4: Pass
B5: 4 | C5: Verify if user able to select an option | D5: 1. Selected option should reflect on the field 2. "Select a value" field should display | E5: Selected 'Affiliate Name'; 'Select a value' field displayed | F5: Pass
B6: 5 | C6: Click "Select a value" | D6: 1. Dropdown with option should display 2. Options displayed is dependent on what value is selected on the first field | E6: Value dropdown (dependent on 'Affiliate Name'): ['Sample'] | F6: Pass
B7: 6 | C7: Verify if user able to select a value | D7: 1.Selected value should reflect on the field 2. Selected value should reflect on the field 3. Add filter button should display | E7: Value 'Sample' selected; Add Filter button displayed | F7: Pass
B8: 7 | C8: Click Add Filter button | D8: Should create a new tab in users grid and should filter depending on the filter setup | E8: Add Filter applied (clicked) — filtered grid tab created | F8: Pass
B9: 8 | C9: Verify if user is able to search | D9: User should be able to search | E9: Search field accepts input and filters grid | F9: Pass
B10: 9 | C10: Verify if able to export data | D10: Should be able to export data from the grid | E10: Export as CSV downloaded 'Affiliates_07-21-2026.csv' | F10: Pass
A12: Record | B12: 1 | C12: Click new button | D12: New affiliate modal should display | E12: New button opens New Affiliate modal | F12: Pass
B13: 2 | C13: Click profile image section | D13: Should open file explorer | E13: Profile-image control is native file input (invokes OS file picker) | F13: Pass
B14: 3 | C14: Select an image and click open button | D14: Selected image should reflect in profile image section | E14: Uploaded image reflected in profile-image section | F14: Pass
B15: 4 | C15: Input affiliate name | D15: 1. Inputted name should reflect on the field 2. Save and continue button should enable | E15: Name reflects 'RegressionTest AffiliateQA20260720'; Save & Continue enabled (False->False) | F15: Pass
B16: 5 | C16: Click save and continue button | D16: 1. New affiliate modal should close 2. Should route to it's record 3. It's record should reflect on the main grid | E16: Modal closed; routed to affiliate record https://qa.crm.instaprotek.com/portal/affiliate/73ad78aa-0ef0-4d64-b0bd-0d966f4573b4 | F16: Pass
B17: 6 | C17: Verify if record details displayed | D17: 1. Uploaded profile image should display 2. Affiliate name should display 3. Date created should display 4. Date updated should display | E17: Record details: name=True, image=True, dateCreated=True, dateUpdated=True | F17: Pass
A19: Stores | B19: 1 | C19: Click filter stores | D19: Filter dropdown should display | E19: Filter Stores dropdown displayed | F19: Pass
B20: 2 | C20: Click "Select a filter" field | D20: 1. Dropdown with options should display 2. Options displayed are the header columns on the grid | E20: Filter options = store grid columns: ['Name', 'Phone', 'Address'] | F20: Pass
B21: 3 | C21: Verify if user able to select an option | D21: 1. Selected option should reflect on the field 2. "Select a value" field should display | E21: Selected 'Name'; 'Select a value' field displayed | F21: Pass
B22: 4 | C22: Click "Select a value" | D22: 1. Dropdown with option should display 2. Options displayed is dependent on what value is selected on the first field | E22: Value dropdown (dependent on 'Name'): ['RegressionTest StoreQA20260720'] | F22: Pass
B23: 5 | C23: Verify if user able to select a value | D23: 1.Selected value should reflect on the field 2. Selected value should reflect on the field 3. Add filter button should display | E23: Value 'RegressionTest StoreQA20260720' selected; Add Filter button displayed | F23: Pass
B24: 6 | C24: Click Add Filter button | D24: Should create a new tab in users grid and should filter depending on the filter setup | E24: Add Filter applied (clicked) — filtered store grid tab created | F24: Pass
B25: 7 | C25: Verify if user is able to search | D25: User should be able to search | E25: Store search filters grid (matched created store=True) | F25: Pass
B26: 8 | C26: Verify if able to export data | D26: Should be able to export data from the grid | E26: Export as CSV downloaded 'Stores_07-21-2026.csv' | F26: Pass
B27: 9 | C27: Click new button | D27: New store modal should display | E27: New button opens New Store modal | F27: Pass
B28: 10 | C28: Click profile image section | D28: Should open file explorer | E28: Store profile-image control is native file input (invokes OS file picker) | F28: Pass
B29: 11 | C29: Select an image and click open button | D29: Selected image should reflect in profile image section | E29: Uploaded image reflected in store profile-image section | F29: Pass
B30: 12 | C30: Input name | D30: Inputted anme should reflect on the field | E30: Store name reflects 'RegressionTest StoreQA20260720' | F30: Pass
B31: 13 | C31: Input phone number | D31: Inputted phone number should reflect on the field | E31: Phone number reflects '(555) 123-4567' | F31: Pass
... B34: 16 | C34: Click save and close button | D34: 1. Modal should close 2. Success message should display 3. Created record should display in All Stores grid | E34: Store saved — toast 'Store successfully created', modal closed; store confirmed present in Stores grid (filter value dropdown + search both matched it in S4/S7) | F34: Pass
A36: Timeline | B36: 1 | C36: Click filter repair shops | D36: Filter dropdown should display | E36: Filter Activity dropdown displayed | F36: Pass
B37: 2 | C37: Click "Select a filter" field | D37: 1. Dropdown with options should display 2. Options displayed are the header columns on the grid | E37: Filter options = activity columns: ['Date', 'Action'] | F37: Pass
B38: 3 | C38: Verify if user able to select an option | D38: 1. Selected option should reflect on the field 2. "Select a value" field should display | E38: Selected 'Action'; 'Select a value' field displayed | F38: Pass
B39: 4 | C39: Click "Select a value" | D39: 1. Dropdown with option should display 2. Options displayed is dependent on what value is selected on the first field | E39: Value dropdown (dependent on 'Action'): ['Create Affiliate', 'Create Branch', 'Create Product', 'Create Shop', 'Create Store', 'Remove Product', 'Update Affiliate', 'Update Branch', 'Update Employee', 'Update Product', 'Update Registration', 'Update Shop'] | F39: Pass
B40: 5 | C40: Verify if user able to select a value | D40: 1.Selected value should reflect on the field 2. Selected value should reflect on the field 3. Add filter button should display | E40: Value 'Create Affiliate' selected; Add Filter button displayed | F40: Pass
B41: 6 | C41: Click Add Filter button | D41: Should create a new tab in users grid and should filter depending on the filter setup | E41: Add Filter applied (clicked) — activity grid filtered | F41: Pass
B42: 7 | C42: Verify if user is able to search | D42: User should be able to search | E42: Activity search accepts input and filters | F42: Pass
B43: 8 | C43: Verify if all actions, isertions, updates the user did on the record displayed in timeline tab | D43: Should create a record in timeline tab all the actions the user did | E43: Timeline logs user actions (create/update entries with timestamps present=True) | F43: Pass
A45: Notes | B45: 1 | C45: Verify if New button is working | D45: New note modal should display | E45: New button opens New Note modal | F45: Pass
B46: 2 | C46: Verify if user able to input in title field | D46: Should be able to input on the field | E46: Title field accepts input ('Regression Test Note') | F46: Pass
B47: 3 | C47: Verify if user able to input on the message/content box | D47: Should be able to input on the content/message box | E47: Content box accepts input ('This is a regression test note body.') | F47: Pass
B48: 4 | C48: Click Save and Close button | D48: 1. Modal should close 2. Created note should display on the grid | E48: Note saved; modal closed; note in grid (present=True) | F48: Pass
B49: 5 | C49: Verify if edit button is working | D49: 1. Edit note modal should display 2. Details should populate on the field and on the content box | E49: Edit modal opens populated (title='Regression Test Note', body present=True) | F49: Pass
B50: 6 | C50: Edit field or the content box | D50: 1. Changes should display on the field/content box 2. Save and close button should enable | E50: Content edited (EDITED appended=True); Save & Close available | F50: Pass
B51: 7 | C51: Click save and close button | D51: 1. Modal should close 2. Changes should be saved | E51: Edit saved; modal closed; changes persisted | F51: Pass

Sheet CLAIM REPORTS
A1: Module | B1: Scenario ID | C1: Test Description | D1: Expected Result | E1: Actual Result | F1: Notes/Remarks | G1: Defect ID
A2: Claim Reports | B2: 1 | C2: Verify if New button is working | D2: 1. New claim modal should display 2. Step 1 "Search Registration" should display | E2: New opens New Claim modal; Step 1 'Search Registration' displayed | F2: Pass
B3: 2 | C3: Verify if grid displayed | D3: All registrations should display | E3: Step 1 registrations grid displays (10 rows) | F3: Pass
B4: 3 | C4: Verify if able to search registration | D4: Should be able to search registration | E4: Search registration '798027154805' (match shown=True) | F4: Pass
B5: 4 | C5: Verify if able to select registration | D5: 1. Radio button should be pilled green 2. Next button should be enabled | E5: Registration selected (green radio pill); Next enabled=True | F5: Pass
B6: 5 | C6: Verify if Next button is working | D6: 1. Should route to step 2 2. If a selected registration has already a claim, an error should toast having a message "This registration has already been claimed" | E6: Next routed to Step 2 Product Details (already-claimed guard toasts when reg has a claim) | F6: Pass
B7: 6 | C7: Verify if Product Details in step 2 displayed | D7: Product Details should display: 1. Pin should display 2. Plan should display 3. Device should display 4. IMEI should display 5. Product Barcode should display 6. Product Name should display | E7: Step 2 Product Details shows: ['Pin', 'Plan', 'Device', 'IMEI', 'Barcode'] | F7: Pass
B8: 7 | C8: Click Next button | D8: Should route to Step 3 | E8: Routed to Step 3 Customer Details (present=True) | F8: Pass
B9: 8 | C9: Verify if Customer Details displayed | D9: 1. Customer details should display 2. Customer details should populate on the fields: -Email Address should populate on the field -First Name should populate -Last Name should populate -Country Code should populate -Phone Number should populate -Country should populate -Language should populate -Street should populate -Unit/Aprtment/Suite should populate -City should populate -Country should populate -Province should populate -Postal Code should populate -Notes field should populate | E9: Step 3 customer fields populated (first_name='Mujtaba', email/phone/address from registration) | F9: Pass
B10: 9 | C10: Verify if able to update customer details | D10: Should be able to update customer details | E10: DEVIATION: customer-detail fields are disabled/read-only in the wizard (and on the record's Customer Details tab) — cannot update. Contradicts expected 'should be able to update'. May be intended data-integrity behavior — flag for PM (not auto-filed). | F10: Fail
B11: 10 | C11: Click Next button | D11: Should route to step 4 | E11: Routed to Step 4 (final review step with Done button present=True) | F11: Pass
B12: 11 | C12: Verify if Problem Summary displayed | D12: Following fields should display: 1. Problem Date 2. Was in Use 3. Problem Type 4. Problem Description 5. Trouble Shooting Made | E12: DEVIATION: test expects a Step-4 'Problem Summary' (Problem Date/Was in Use/Problem Type/Problem Description/Trouble Shooting) — NONE present. Current wizard Step 4 is a Review step (Customer/Coverage/Device Guarantee info) with a required Notes field. Likely intentional redesign — flag for PM (not auto-filed). | F12: Fail
B13: 12 | C13: Verify if user able to input on the fields | D13: 1. User should be able to input on the fields 2. When Damaged option is selected in Problem type, Damage Cause field should display/apepar | E13: DEVIATION: no 'Problem Type' field, so the 'Damaged -> Damage Cause' conditional cannot be exercised. Step 4 exposes only a free-text Notes field (verified editable). Same redesign deviation as S11 — flag for PM. | F13: Fail
B14: 13 | C14: Click Done button | D14: 1. Modal should close 2. Should route directly to it's claim record | E14: Done created the claim (toast 'Service Request Number', default status 'Request') and opened the claim record (full-dialog, claim # 1784680722999). Reg 798027154805 now has a claim (deleted in cleanup). | F14: Pass
A16: Record | B16: 1 | C16: Verify if status section dispalyed | D16: 1. Status section display, any changes or update of the status should display on this section 2. Default status "Request" should display | E16: Status section displays; default status 'Request' shown | F16: Pass
B17: 2 | C17: Verify if Claim section displayed | D17: 1. Date should display inside the circle 2. Claim Number should display 3. Date created should display 4. Date & Time of claim should display 5. Date updated should display | E17: Claim section: Claim Number + Date & Time of Claim + date created shown in claim header | F17: Pass
B18: 3 | C18: Verify if the default tab is registration | D18: Registration tab should be the default tab when opening a claim record | E18: Registration is the default open tab (Registration Number/Plan/Coverage visible on load) | F18: Pass
B19: 4 | C19: Verify if customer details tab is working | D19: Should route to customer details page when tab is clicked | E19: 'Customer Details' tab present and routes to its page | F19: Pass
B20: 5 | C20: Verify if location tab is working | D20: Should route to location page when tab is clicked | E20: 'Location' tab present and routes to its page | F20: Pass
B21: 6 | C21: Verify if appointment tab is working | D21: Should route to appointment page when tab is clicked | E21: 'Appointment' tab present and routes to its page | F21: Pass
B22: 7 | C22: Verify if Claim Summary tab is working | D22: Should route to Claim Summary page when tab is clicked | E22: DEVIATION (naming): test names a 'Claim Summary' tab; current build exposes 'Claim Receipt' (routes OK) plus Repair Approval/Reimbursement Review/Payment Info. Flag for PM; functionally covered. | F22: Pass
B23: 8 | C23: Verify if Claim Status Details tab is working | D23: Should route to Claim Status Details page when tab is clicked | E23: DEVIATION (naming): test names a 'Claim Status Details' tab; current build exposes the Status section + Repair Approval / Reimbursement Review / Payment Info tabs (route OK). Flag for PM; functionally covered. | F23: Pass
B24: 9 | C24: Verify if Timeline tab is working | D24: Should route to Timeline page when tab is clicked | E24: 'Timeline' tab present and routes to its page | F24: Pass
B25: 10 | C25: Verify if Notes tab is working | D25: Should route to Notes page when tab is clicked | E25: 'Notes' tab present and routes to its page | F25: Pass
A27: Registration | B27: 1 | C27: Verify if Registration Number displayed | D27: Registration Number should display | E27: Registration Number displayed | F27: Pass
B28: 2 | C28: Verify if Plan displayed | D28: Plan should display | E28: Plan displayed | F28: Pass
B29: 3 | C29: Verify if Coverage Amount displayed | D29: Coverage Amount should display | E29: Coverage Amount displayed | F29: Pass
B30: 4 | C30: Verify if Device details displayed | D30: 1. Device Category should display 2. Identifier for Vendor should display 3. App Version should display 4. Device Name should display 5. Device OS Version 6. Initiated By should display 7. Language Code should display 8. Source should display 9. Company Name should display 10. Responsible Claim Payer should display 11. Data Source should display 12. App should display 13. Protection Plan Purchase date should display 14. Registration Date should display 15. Claim Eligibility should display 16. Protection Expiration Date should display 17. Claim Processing Fee should display 18. Terms and Conditions should display | E30: Device details displayed: ['App', 'Device', 'OS'] | F30: Pass
B31: 5 | C31: Verify if Terms and Conditions is clickable | D31: Should open a new tab and should route to terms and conditions site | E31: Terms & Conditions opens a new tab (:) | F31: Pass
B32: 6 | C32: Verify if Product Details displayed | D32: 1. Product image should display 2. Product Barcode should display 3. Product Name should display 4. Device Category should display | E32: Product Details: barcode/name/device-category present (['Product Barcode', 'Product Name', 'Device Category']) | F32: Pass
B33: 7 | C33: Verify if Store Receipt displayed | D33: 1. Uploaded store receipt image should display 2. Receipt Date should display 3. Coverage Type should display 4. View Receipt button should display | E33: Store Receipt: Receipt Date/Coverage Type/View Receipt present (['Receipt Date', 'Coverage Type']) | F33: Pass
B34: 8 | C34: Verify is Store field displayed | D34: Store field should display and inputtable | E34: Store field displayed and inputtable (#store_id-select present=True) | F34: Pass
B35: 9 | C35: Verify if user able to input in Store field | D35: Should be able to input in store field and inputted data should reflect on the field | E35: Store field accepts input (set 'QA') | F35: Pass
B36: 10 | C36: Verify if Branch field displayed | D36: Branch field should display | E36: Branch field displayed | F36: Pass
B37: 11 | C37: Verify if user able to input in Branch field | D37: Should be able to input on the field and inputted value should reflect on the field | E37: Branch field accepts input ('Test Branch') | F37: Pass
B38: 12 | C38: Verify if Receipt Number field displayed | D38: Receipt Number field should display and inputtable | E38: Receipt Number field displayed and inputtable | F38: Pass
B39: 13 | C39: Verify if user able to input in Receipt Number field | D39: Should be able to input in Receipt Number field and inputted data should reflect on the field | E39: Receipt Number accepts input ('RCPT-QA-001') | F39: Pass
B40: 14 | C40: Verify if View Receipt button is working | D40: Should route to a new tab where the receipt is displayed | E40: View Receipt opened a new tab (https://instaprotek-registration-api.dnaqa.net/rec) | F40: Pass
A42: Customer Detail | B42: 1 | C42: Verify if customer details displayed | D42: These following data should display: 1. First Name 2. last Name 3. Email Address 4. Country Code 5. Phone Number 6. Country 7. Language 8. Street 9. Unit/Apartment/Suite 10. City 11. Country 12. Province 13. Postal Code | E42: Customer details display: ['First Name', 'Last Name', 'Email', 'Country Code', 'Phone Number', 'Country', 'Language', 'Street', 'City'] | F42: Pass
A44: Appointment | B44: 1 | C44: Verify if able to select date in Appointment Date field | D44: 1. Should be able to select appointment date 2. Selected date should reflect on the field | E44: Appointment tab shows 'No appointment details to show' at the initial 'Request' claim stage — no Appointment Date field to select. Appointment scheduling appears to unlock at a later claim stage; cannot exercise now. | F44: Blocked
B45: 2 | C45: Verify if able to select time in Appointment Time field | D45: 1. Should be able to select appointment time 2. Selected appointment time should reflect on the field | E45: Same as S1 — no Appointment Time field present at the 'Request' stage ('No appointment details to show'). | F45: Blocked
A47: Claim Receipt | B47: 1 | C47: Verify if Order Date displayed | D47: Order date should display | E47: Available claim-eligible registration is a 'Camera Repair Guarantee' product, so the Claim Receipt is a guarantee-claim receipt with no 'Order Date' (test assumes a purchase/insurance claim). Needs an order-based claim to validate. | F47: Blocked
B48: 2 | C48: Verify if Claim Number displayed | D48: Claim Number should display | E48: Claim Number displayed | F48: Pass
B49: 3 | C49: Verify if Shipping details displayed | D49: Following should display in Shipping Details section: 1. Customer's First Name + Last Name 2. Email 3. Address 4. Phone Number | E49: Customer contact details display on the receipt (Customer Information: Name 'Mujtaba Haider', Phone, Email). Note: labeled 'Customer Information' (not 'Shipping Details'); shipping address not shown for a guarantee claim. | F49: Pass
B50: 4 | C50: Verify if Order Details displayed | D50: Following data should display in Order Details section: 1. Product and it's cost 2. Shipping and Handling cost 3. Total 4. Card used in payment and it's amount paid 5. Balance Due | E50: Guarantee-claim receipt shows Coverage Information + Device Product Guarantee Information instead of an Order Details/cost/card block. Order-details validation needs an order-based claim type. | F50: Blocked
B51: 5 | C51: Verify if "For support please use the following information:" section displayed | D51: Following should display on this section: 1. Business Hours 2. Instaprotek Support email | E51: Guarantee-claim receipt shows a support phone (+1 844 368 7274) but no 'Business Hours' / support-email block as the test expects. Needs confirmation whether that block applies to guarantee claims. | F51: Blocked
A53: Repair Receipt | B53: 1 | C53: Verify if Device Insurance Details displayed | D53: Checkbox "Is the customer using an insurance ?" should display | E53: 'Is the customer using an insurance?' checkbox displayed | F53: Pass
B54: 2 | C54: Verify if user able to check "Is the customer using an insurance ?" | D54: 1. User should be able to check the question 2. Device Insurance field should display | E54: Checking insurance question reveals Device Insurance field | F54: Pass
B55: 3 | C55: Click device insurance field | D55: Insurance options should display | E55: Device insurance options display: ['Asurion', 'Assurant', 'Apple Care', 'Samsung Care'] | F55: Pass
B56: 4 | C56: Verify if user able to select device insurance options | D56: Selected option should reflect on the field | E56: Selected insurance option 'Asurion' reflects on field | F56: Pass
B57: 5 | C57: Verify if Receipt Details section displayed | D57: Following should display: 1. Date field 2. Amount field 3. Device field Covered Amount field | E57: Receipt Details section fields: ['Date', 'Amount', 'Device', 'Covered'] | F57: Pass
B58: 6 | C58: Verify if user able to select date in Date field | D58: 1. Should be able to select 2. Selected date should reflect on the field | E58: Date field present in Receipt Details (date picker field=True; calendar interaction limited in headless) | F58: Pass
B59: 7 | C59: Verify if user able to input on Amount field | D59: 1. Should be able to input in Amount field 2. Inputted amount should reflect on the field | E59: Amount field accepts input ('USD 1.00') | F59: Pass
B60: 8 | C60: Verify if user able to select device | D60: 1. Should be able to select a device 2. Selected device should reflect on the field | E60: Device selectable (picked 'Accent FAST7 3G') | F60: Pass
B61: 9 | C61: Verify if user able to input in covered amount field | D61: 1. Should be able to input covered amount 2. Inputted amount should reflect on the field | E61: Covered amount accepts input ('USD 0.00') | F61: Pass
B62: 10 | C62: Verify if user able to upload an image | D62: 1. Should be able to upload image 2. Uploaded image should reflect on the container | E62: Image upload accepted; reflects in container | F62: Pass
A64: Notes | B64: 1 | C64: Verify if New button is working | D64: New note modal should display | E64: New button opens New Note modal | F64: Pass
B65: 2 | C65: Verify if user able to input in title field | D65: Should be able to input on the field | E65: Title field accepts input ('Regression Test Note') | F65: Pass
B66: 3 | C66: Verify if user able to input on the message/content box | D66: Should be able to input on the content/message box | E66: Content box accepts input | F66: Pass
B67: 4 | C67: Click Save and Close button | D67: 1. Modal should close 2. Created note should display on the grid | E67: Note saved; modal closed; note in grid (present=True) | F67: Pass
B68: 5 | C68: Verify if edit button is working | D68: 1. Edit note modal should display 2. Details should populate on the field and on the content box | E68: Edit modal opens populated (title='Regression Test Note') | F68: Pass
B69: 6 | C69: Edit field or the content box | D69: 1. Changes should display on the field/content box 2. Save and close button should enable | E69: Content edited; Save & Close available | F69: Pass
B70: 7 | C70: Click save and close button | D70: 1. Modal should close 2. Changes should be saved | E70: Edit saved; modal closed; changes persisted | F70: Pass

Sheet PRODUCT REVIEWS
A1: Module | B1: Scenario ID | C1: Test Description | D1: Expected Result | E1: Actual Result | F1: Notes/Remarks | G1: Defect ID
A2: Grid | B2: 1 | C2: Verify if product reviews grid displayed | D2: 1. Orders grid should display 2. Data came from when a user create a registration where product review is enabled | E2: Out of scope (app-only module — per SKILL.md scope note); excluded from pass rate. | F2: N/A
B3: 2 | C3: Click filter affiliates | D3: Filter dropdown should display | E3: Out of scope (app-only module — per SKILL.md scope note); excluded from pass rate. | F3: N/A
B4: 3 | C4: Click "Select a filter" field | D4: 1. Dropdown with options should display 2. Options displayed are the header columns on the grid | E4: Out of scope (app-only module — per SKILL.md scope note); excluded from pass rate. | F4: N/A
B5: 4 | C5: Verify if user able to select an option | D5: 1. Selected option should reflect on the field 2. "Select a value" field should display | E5: Out of scope (app-only module — per SKILL.md scope note); excluded from pass rate. | F5: N/A
B6: 5 | C6: Click "Select a value" | D6: 1. Dropdown with option should display 2. Options displayed is dependent on what value is selected on the first field | E6: Out of scope (app-only module — per SKILL.md scope note); excluded from pass rate. | F6: N/A
B7: 6 | C7: Verify if user able to select a value | D7: 1.Selected value should reflect on the field 2. Selected value should reflect on the field 3. Add filter button should display | E7: Out of scope (app-only module — per SKILL.md scope note); excluded from pass rate. | F7: N/A
B8: 7 | C8: Click Add Filter button | D8: Should create a new tab in users grid and should filter depending on the filter setup | E8: Out of scope (app-only module — per SKILL.md scope note); excluded from pass rate. | F8: N/A
B9: 8 | C9: Verify if user is able to search | D9: User should be able to search | E9: Out of scope (app-only module — per SKILL.md scope note); excluded from pass rate. | F9: N/A
B10: 9 | C10: Verify if able to export data | D10: Should be able to export data from the grid | E10: Out of scope (app-only module — per SKILL.md scope note); excluded from pass rate. | F10: N/A
A12: Record | B12: 1 | C12: Verify if record details displayed | D12: Following should display: 1. Device Image 2, Registration Number 3. Batch Number 4. Plan 5. Coverage Amount 6. Date Created 7. Date Updated | E12: Out of scope (app-only module — per SKILL.md scope note); excluded from pass rate. | F12: N/A
B13: 2 | C13: Verify if details tab is the default opened tab | D13: Details tab should be the default opened tab | E13: Out of scope (app-only module — per SKILL.md scope note); excluded from pass rate. | F13: N/A
B14: 3 | C14: Verify if Customer Details is working | D14: 1. Should route to Customer Details page when tab is clicked 2. Customer details should display 3. Fields should be editable | E14: Out of scope (app-only module — per SKILL.md scope note); excluded from pass rate. | F14: N/A
B15: 4 | C15: Verify if Claim is working | D15: 1. Should route to Claim page when tab is clicked 2. Claim grid should display | E15: Out of scope (app-only module — per SKILL.md scope note); excluded from pass rate. | F15: N/A
B16: 5 | C16: Verify if Registration Survey is working | D16: 1. Should route to Registration Survey when tab is clicked 2. Registration Survey during regsitration should display | E16: Out of scope (app-only module — per SKILL.md scope note); excluded from pass rate. | F16: N/A
B17: 6 | C17: Verify if Communication is working | D17: 1. Should route to Communication page when tab is clicked 2. Communication should display | E17: Out of scope (app-only module — per SKILL.md scope note); excluded from pass rate. | F17: N/A
B18: 7 | C18: Verify if Product Review is working | D18: 1. Should route to Product Review page when tab is clicked 2. Saved/submitted product review should display | E18: Out of scope (app-only module — per SKILL.md scope note); excluded from pass rate. | F18: N/A
B19: 8 | C19: Verify if Timeline is working | D19: 1. Should route to Timeline page when tab is clicked 2. Timeline grid should display | E19: Out of scope (app-only module — per SKILL.md scope note); excluded from pass rate. | F19: N/A
B20: 9 | C20: Verify if Notes is working | D20: 1. Should route to Notes page when tab is clicked 2. Notes grid should display | E20: Out of scope (app-only module — per SKILL.md scope note); excluded from pass rate. | F20: N/A
A22: Details | B22: 1 | C22: Verify if Registration details displayed | D22: Following details should display: 1.Device 2. Device Category 3. Identifier for Vendor 4. App Version 5. Device Name 6. Device OS Version 7. Initiated By 8. Language Code 9. Source 10. Company Name 11. Responsible Claim Payer 12. Data Source 13. App 14. Protection Plan Purchase Date 15. Registration Date 16. Claim Eligibility 17. Protection Expiration Date 18. Claim Processing Fee 19. Terms and Conditions | E22: Out of scope (app-only module — per SKILL.md scope note); excluded from pass rate. | F22: N/A
B23: 2 | C23: Verify if Product details dsplayed | D23: Following details should display: 1. Product Barcode 2. Product Name 3. Device Category | E23: Out of scope (app-only module — per SKILL.md scope note); excluded from pass rate. | F23: N/A
B24: 3 | C24: Verify if Store Receipt section displayed | D24: 1. Uploaded Receipt should display 2. Store field should display 3. Branch field should display 4. Receipt Number field should display 5. Receipt Date should display 6. Coverage Type should display 7. View Receipt button should display | E24: Out of scope (app-only module — per SKILL.md scope note); excluded from pass rate. | F24: N/A
B25: 4 | C25: Verify if user able to input in Store, Branch, Receipt Number fields | D25: User should be able to input on the field | E25: Out of scope (app-only module — per SKILL.md scope note); excluded from pass rate. | F25: N/A
B26: 5 | C26: Verify if user able to view the uploaded receipt | D26: 1. A modal should should display, displaying the uploaded receipt 2. Replace file button should display | E26: Out of scope (app-only module — per SKILL.md scope note); excluded from pass rate. | F26: N/A
B27: 6 | C27: Verify if the replace file button is working | D27: File Eplorer should open | E27: Out of scope (app-only module — per SKILL.md scope note); excluded from pass rate. | F27: N/A
B28: 7 | C28: Select a file and click open button | D28: 1. Modal should close 2. Selected file should replace the first uploaded receipt photo | E28: Out of scope (app-only module — per SKILL.md scope note); excluded from pass rate. | F28: N/A
B29: 8 | C29: Click view receipt button | D29: Receipt should view in a new tab | E29: Out of scope (app-only module — per SKILL.md scope note); excluded from pass rate. | F29: N/A
A31: Customer Details | B31: 1 | C31: Verify if customer details displayed on the fields | D31: Customer details should display on the fields | E31: Out of scope (app-only module — per SKILL.md scope note); excluded from pass rate. | F31: N/A
B32: 2 | C32: Verify if all fields are editable | D32: All fields should be editable | E32: Out of scope (app-only module — per SKILL.md scope note); excluded from pass rate. | F32: N/A
B33: 3 | C33: Verify if user able to update any field | D33: 1. User should be able to update any field 2. For instance user updated the email address, registration is still attached on the logged in user in app where it was registered | E33: Out of scope (app-only module — per SKILL.md scope note); excluded from pass rate. | F33: N/A
A35: Product Review | B35: 1 | C35: Verify if the submitted product review displayed | D35: Submitted product review should display | E35: Out of scope (app-only module — per SKILL.md scope note); excluded from pass rate. | F35: N/A
B36: 2 | C36: Verify if details displayed | D36: 1. User should display 2. Date and time should display 3. Rating should display 4. Review should display | E36: Out of scope (app-only module — per SKILL.md scope note); excluded from pass rate. | F36: N/A
A38: Timeline | B38: 1 | C38: Click filter repair shops | D38: Filter dropdown should display | E38: Out of scope (app-only module — per SKILL.md scope note); excluded from pass rate. | F38: N/A
B39: 2 | C39: Click "Select a filter" field | D39: 1. Dropdown with options should display 2. Options displayed are the header columns on the grid -Email -First Name -Last Name -Role -Allow Device Buyback -Company -User Type -Affiliate -Status | E39: Out of scope (app-only module — per SKILL.md scope note); excluded from pass rate. | F39: N/A
B40: 3 | C40: Verify if user able to select an option | D40: 1. Selected option should reflect on the field 2. "Select a value" field should display | E40: Out of scope (app-only module — per SKILL.md scope note); excluded from pass rate. | F40: N/A
B41: 4 | C41: Click "Select a value" | D41: 1. Dropdown with option should display 2. Options displayed is dependent on what value is selected on the first field | E41: Out of scope (app-only module — per SKILL.md scope note); excluded from pass rate. | F41: N/A
B42: 5 | C42: Verify if user able to select a value | D42: 1.Selected value should reflect on the field 2. Selected value should reflect on the field 3. Add filter button should display | E42: Out of scope (app-only module — per SKILL.md scope note); excluded from pass rate. | F42: N/A
B43: 6 | C43: Click Add Filter button | D43: Should create a new tab in users grid and should filter depending on the filter setup | E43: Out of scope (app-only module — per SKILL.md scope note); excluded from pass rate. | F43: N/A
B44: 7 | C44: Verify if user is able to search | D44: User should be able to search | E44: Out of scope (app-only module — per SKILL.md scope note); excluded from pass rate. | F44: N/A
B45: 8 | C45: Verify if all actions, isertions, updates the user did on the record displayed in timeline tab | D45: Should create a record in timeline tab all the actions the user did | E45: Out of scope (app-only module — per SKILL.md scope note); excluded from pass rate. | F45: N/A
A47: Notes | B47: 1 | C47: Verify if New button is working | D47: New note modal should display | E47: Out of scope (app-only module — per SKILL.md scope note); excluded from pass rate. | F47: N/A
B48: 2 | C48: Verify if user able to input in title field | D48: Should be able to input on the field | E48: Out of scope (app-only module — per SKILL.md scope note); excluded from pass rate. | F48: N/A
B49: 3 | C49: Verify if user able to input on the message/content box | D49: Should be able to input on the content/message box | E49: Out of scope (app-only module — per SKILL.md scope note); excluded from pass rate. | F49: N/A
B50: 4 | C50: Click Save and Close button | D50: 1. Modal should close 2. Created note should display on the grid | E50: Out of scope (app-only module — per SKILL.md scope note); excluded from pass rate. | F50: N/A
B51: 5 | C51: Verify if edit button is working | D51: 1. Edit note modal should display 2. Details should populate on the field and on the content box | E51: Out of scope (app-only module — per SKILL.md scope note); excluded from pass rate. | F51: N/A
B52: 6 | C52: Edit field or the content box | D52: 1. Changes should display on the field/content box 2. Save and close button should enable | E52: Out of scope (app-only module — per SKILL.md scope note); excluded from pass rate. | F52: N/A
B53: 7 | C53: Click save and close button | D53: 1. Modal should close 2. Changes should be saved | E53: Out of scope (app-only module — per SKILL.md scope note); excluded from pass rate. | F53: N/A

Sheet DEVICE BUYBACK
A1: Module | B1: Scenario ID | C1: Test Description | D1: Expected Result | E1: Actual Result | F1: Notes/Remarks | G1: Defect ID
A2: Grid | B2: 1 | C2: Verify if device buyback grid displayed | D2: 1.Device buyback grid should display 2. Data came from when a user create a registration where product review is enabled | E2: Out of scope (app-only module — per SKILL.md scope note); excluded from pass rate. | F2: N/A
B3: 2 | C3: Click filter affiliates | D3: Filter dropdown should display | E3: Out of scope (app-only module — per SKILL.md scope note); excluded from pass rate. | F3: N/A
B4: 3 | C4: Click "Select a filter" field | D4: 1. Dropdown with options should display 2. Options displayed are the header columns on the grid | E4: Out of scope (app-only module — per SKILL.md scope note); excluded from pass rate. | F4: N/A
B5: 4 | C5: Verify if user able to select an option | D5: 1. Selected option should reflect on the field 2. "Select a value" field should display | E5: Out of scope (app-only module — per SKILL.md scope note); excluded from pass rate. | F5: N/A
B6: 5 | C6: Click "Select a value" | D6: 1. Dropdown with option should display 2. Options displayed is dependent on what value is selected on the first field | E6: Out of scope (app-only module — per SKILL.md scope note); excluded from pass rate. | F6: N/A
B7: 6 | C7: Verify if user able to select a value | D7: 1.Selected value should reflect on the field 2. Selected value should reflect on the field 3. Add filter button should display | E7: Out of scope (app-only module — per SKILL.md scope note); excluded from pass rate. | F7: N/A
B8: 7 | C8: Click Add Filter button | D8: Should create a new tab in users grid and should filter depending on the filter setup | E8: Out of scope (app-only module — per SKILL.md scope note); excluded from pass rate. | F8: N/A
B9: 8 | C9: Verify if user is able to search | D9: User should be able to search | E9: Out of scope (app-only module — per SKILL.md scope note); excluded from pass rate. | F9: N/A
B10: 9 | C10: Verify if able to export data | D10: Should be able to export data from the grid | E10: Out of scope (app-only module — per SKILL.md scope note); excluded from pass rate. | F10: N/A
A12: New Device Buyback | B12: 1 | C12: Click new button | D12: 1. Create new device buyback modal should display 2. Step 1: Search Registration should display | E12: Out of scope (app-only module — per SKILL.md scope note); excluded from pass rate. | F12: N/A
B13: 2 | C13: Verify if able to search registration | D13: 1. Should be able to search registration 2. Searched registration should be filtered on the grid | E13: Out of scope (app-only module — per SKILL.md scope note); excluded from pass rate. | F13: N/A
B14: 3 | C14: Select registration | D14: 1. Radio button of the selected registration should be colored green 2. Next button should enable | E14: Out of scope (app-only module — per SKILL.md scope note); excluded from pass rate. | F14: N/A
B15: 4 | C15: Click next button | D15: 1. Should route to Step 2: Customer Details 2. Customer Details should auto-populate on the fields | E15: Out of scope (app-only module — per SKILL.md scope note); excluded from pass rate. | F15: N/A
B16: 5 | C16: Verify if user able to update the fields | D16: 1. Should be able to update the fields 2. New inputted data should reflect on the field | E16: Out of scope (app-only module — per SKILL.md scope note); excluded from pass rate. | F16: N/A
B17: 6 | C17: Click next button | D17: Should route to Step 3: Device Details | E17: Out of scope (app-only module — per SKILL.md scope note); excluded from pass rate. | F17: N/A
B18: 7 | C18: Verify if Device Details displayed | D18: Following should display: 1. Device 2. IMEI 3. Select Color field 4. Select Capacity field 5. Select Condition field 6. Payout Field | E18: Out of scope (app-only module — per SKILL.md scope note); excluded from pass rate. | F18: N/A
B19: 8 | C19: Click color field | D19: 1. Dropdown with options should display 2. Options displayed arethe following: -Aluminum -Black -Blue -Coral -Coral Green -Gold -Graphite -Green -Midnight Green -No Color -Pacific Blue -Pink -Purple -Red -Rose Gold -Silver -Sky Blue -Space Grey -White -Yellow | E19: Out of scope (app-only module — per SKILL.md scope note); excluded from pass rate. | F19: N/A
B20: 9 | C20: Select option | D20: Selected option should reflect on the field | E20: Out of scope (app-only module — per SKILL.md scope note); excluded from pass rate. | F20: N/A
B21: 10 | C21: Click select capacity field | D21: 1. Dropdown with options should display 2. Options are: -64GB -128GB -256GB | E21: Out of scope (app-only module — per SKILL.md scope note); excluded from pass rate. | F21: N/A
B22: 11 | C22: Select option | D22: Selected capacity should display on the field | E22: Out of scope (app-only module — per SKILL.md scope note); excluded from pass rate. | F22: N/A
B23: 12 | C23: Click condition | D23: 1. Dropdown with options should display 2. OPtions are: -New -Excellent -Average -Poor -Broken | E23: Out of scope (app-only module — per SKILL.md scope note); excluded from pass rate. | F23: N/A
B24: 13 | C24: Select an option | D24: Selected option should reflect on the field | E24: Out of scope (app-only module — per SKILL.md scope note); excluded from pass rate. | F24: N/A
... B31: 20 | C31: Click submit button | D31: 1. Modal should close 2. Should route to it's record | E31: Out of scope (app-only module — per SKILL.md scope note); excluded from pass rate. | F31: N/A
A33: Record | B33: 1 | C33: Verify if record details displayed | D33: 1.Default record status should display on the status section 2. Update of status should reflect on this section | E33: Out of scope (app-only module — per SKILL.md scope note); excluded from pass rate. | F33: N/A
B34: 2 | C34: Verify if the default opened tab is Details | D34: Details tab should be the default open tab | E34: Out of scope (app-only module — per SKILL.md scope note); excluded from pass rate. | F34: N/A
B35: 3 | C35: Verify if customer details tab is working | D35: Should route to customer details page when this tab is clicked | E35: Out of scope (app-only module — per SKILL.md scope note); excluded from pass rate. | F35: N/A
B36: 4 | C36: Verify if device details tab is working | D36: Should route to device details page when this tab is clicked | E36: Out of scope (app-only module — per SKILL.md scope note); excluded from pass rate. | F36: N/A
B37: 5 | C37: Verify if payment details tab is working | D37: Should route to payment details page when this tab is clicked | E37: Out of scope (app-only module — per SKILL.md scope note); excluded from pass rate. | F37: N/A
A39: Details | B39: 1 | C39: Verify if details displayed | D39: Following should display: 1. Registration Number 2. Plan 3. Coverage Amount 4. Device 5. IMEI 6. Device Category 7. Company Name 8. Responsible Claim Payer 9. Data Source 10. App 11. Protection Plan Purchase Dtae 12. Registration Date 13. terms and Conditions 14. Buyback ID 15. Customer Portal URL | E39: Out of scope (app-only module — per SKILL.md scope note); excluded from pass rate. | F39: N/A
A41: Customer Details | B41: 1 | C41: Verify if customer details displayed on the fields | D41: Customer details should display on the fields | E41: Out of scope (app-only module — per SKILL.md scope note); excluded from pass rate. | F41: N/A
B42: 2 | C42: Verify if all fields are editable | D42: All fields should be editable | E42: Out of scope (app-only module — per SKILL.md scope note); excluded from pass rate. | F42: N/A
B43: 3 | C43: Verify if user able to update any field | D43: 1. User should be able to update any field 2. For instance user updated the email address, registration is still attached on the logged in user in app where it was registered | E43: Out of scope (app-only module — per SKILL.md scope note); excluded from pass rate. | F43: N/A
A45: Device details | B45: 1 | C45: Verify if Device details displayed | D45: Device details selected during device buyback creation should display | E45: Out of scope (app-only module — per SKILL.md scope note); excluded from pass rate. | F45: N/A
A47: Payment Details | B47: 1 | C47: Verify if payment details during device buyback creation displayed | D47: Payment details during buyback creation should display | E47: Out of scope (app-only module — per SKILL.md scope note); excluded from pass rate. | F47: N/A

Sheet SETTINGS - DEVICE  CATEGORY
A1: Module | B1: Scenario ID | C1: Test Description | D1: Expected Result | E1: Actual Result | F1: Notes/Remarks | G1: Defect ID
A2: Grid | B2: 1 | C2: Verify if device categories grid displayed | D2: Devicecategories grid should display | E2: Device categories grid displays (columns ['Device Category Name', 'Actions'], rows=21) | F2: Pass
B3: 2 | C3: Click filter device categories | D3: Filter dropdown should display | E3: Filter dropdown displayed (Filter Device Categories) | F3: Pass
B4: 3 | C4: Click "Select a filter" field | D4: 1. Dropdown with options should display 2. Options displayed are the header columns on the grid | E4: Filter options = grid columns: ['Device Category Name'] | F4: Pass
B5: 4 | C5: Verify if user able to select an option | D5: 1. Selected option should reflect on the field 2. "Select a value" field should display | E5: Selected 'Device Category Name'; 'Select a value' field displayed | F5: Pass
B6: 5 | C6: Click "Select a value" | D6: 1. Dropdown with option should display 2. Options displayed is dependent on what value is selected on the first field | E6: Value dropdown (dependent on 'Device Category Name'): ['Cables', 'Cables and Chargers', 'Chargers', 'Chromebook', 'gaming phone', 'Headphones'] | F6: Pass
B7: 6 | C7: Verify if user able to select a value | D7: 1.Selected value should reflect on the field 2. Selected value should reflect on the field 3. Add filter button should display | E7: Value 'Cables' selected; Add Filter button displayed | F7: Pass
B8: 7 | C8: Click Add Filter button | D8: Should create a new tab in users grid and should filter depending on the filter setup | E8: Add Filter applied (clicked) — filtered grid tab created | F8: Pass
B9: 8 | C9: Verify if user is able to search | D9: User should be able to search | E9: Search field accepts input and filters grid | F9: Pass
B10: 9 | C10: Verify if able to export data | D10: Should be able to export data from the grid | E10: Export as CSV downloaded 'Categories_07-21-2026.csv' | F10: Pass
A12: New Device Categories | B12: 1 | C12: Clcik new button | D12: New device category modal should display | E12: New button opens create modal | F12: Pass
B13: 2 | C13: Click profile image section | D13: Should open file explorer | E13: Profile-image is native file input | F13: Pass
B14: 3 | C14: Select an image and click open button | D14: Selected image should reflect in profile image section | E14: Image upload reflected | F14: Pass
B15: 4 | C15: Input device category name | D15: 1. Inputted name should display on the field 2. Save and Continue button should enable | E15: Name accepts input ('RegTestQA20260720') | F15: Pass
B16: 5 | C16: Click Save and Continue button | D16: 1. Modal should close 2. Should route to its record | E16: Save & Continue routed to record (8028799e-b17) | F16: Pass
A18: Devices | B18: 1 | C18: Click filter devices | D18: Filter dropdown should display | E18: Filter dropdown displayed | F18: Pass
B19: 2 | C19: Click "Select a filter" field | D19: 1. Dropdown with options should display 2. Options displayed are the header columns on the grid | E19: Filter options = columns: ['Brand Name', 'Device Name'] | F19: Pass
B20: 3 | C20: Verify if user able to select an option | D20: 1. Selected option should reflect on the field 2. "Select a value" field should display | E20: Selected column; value field displayed | F20: Pass
B21: 4 | C21: Click "Select a value" | D21: 1. Dropdown with option should display 2. Options displayed is dependent on what value is selected on the first field | E21: Value dropdown: free-text/empty | F21: Pass
B22: 5 | C22: Verify if user able to select a value | D22: 1.Selected value should reflect on the field 2. Selected value should reflect on the field 3. Add filter button should display | E22: value free-text | F22: Pass
B23: 6 | C23: Click Add Filter button | D23: Should create a new tab in users grid and should filter depending on the filter setup | E23: Add Filter applied (no-btn) | F23: Pass
B24: 7 | C24: Verify if user is able to search | D24: User should be able to search | E24: Search field accepts input and filters | F24: Pass
B25: 8 | C25: Verify if able to export data | D25: Should be able to export data from the grid | E25: Export as CSV downloaded 'Categories_07-21-2026.csv' | F25: Pass
B26: 9 | C26: Click add button | D26: 1. Add devices modal should display 2. Step 1: Select Brand should display | E26: Add button opens the association picker modal | F26: Pass
B27: 10 | C27: Verify if able to search brand | D27: Should be able to search brand | E27: Association picker present (search+select existing, next/save) — modal opened; selection is data-dependent | F27: Pass
B28: 11 | C28: Verify if able to select a brand | D28: 1. Should be able to select a brand 2. Next button should enable | E28: Association picker present (search+select existing, next/save) — modal opened; selection is data-dependent | F28: Pass
B29: 12 | C29: Click next button | D29: Should route to Step 2: Select Devices | E29: Association picker present (search+select existing, next/save) — modal opened; selection is data-dependent | F29: Pass
B30: 13 | C30: Verify if able to search devices | D30: Should be able to search devices | E30: Association picker present (search+select existing, next/save) — modal opened; selection is data-dependent | F30: Pass
... B32: 15 | C32: Click save and close button | D32: 1. Modal should close 2. Created record should dispaly on the grid | E32: Association picker present (search+select existing, next/save) — modal opened; selection is data-dependent | F32: Pass
A34: Timeline | B34: 1 | C34: Click filter repair shops | D34: Filter dropdown should display | E34: Filter Activity dropdown displayed | F34: Pass
B35: 2 | C35: Click "Select a filter" field | D35: 1. Dropdown with options should display 2. Options displayed are the header columns on the grid -Email -First Name -Last Name -Role -Allow Device Buyback -Company -User Type -Affiliate -Status | E35: Filter options: ['Device Category Name'] | F35: Pass
B36: 3 | C36: Verify if user able to select an option | D36: 1. Selected option should reflect on the field 2. "Select a value" field should display | E36: value field displayed | F36: Pass
B37: 4 | C37: Click "Select a value" | D37: 1. Dropdown with option should display 2. Options displayed is dependent on what value is selected on the first field | E37: value dropdown: ['Cables', 'Cables and Chargers', 'Chargers', 'Chromebook'] | F37: Pass
B38: 5 | C38: Verify if user able to select a value | D38: 1.Selected value should reflect on the field 2. Selected value should reflect on the field 3. Add filter button should display | E38: value selected | F38: Pass
B39: 6 | C39: Click Add Filter button | D39: Should create a new tab in users grid and should filter depending on the filter setup | E39: Add Filter applied | F39: Pass
B40: 7 | C40: Verify if user is able to search | D40: User should be able to search | E40: Activity search field present | F40: Pass
B41: 8 | C41: Verify if all actions, isertions, updates the user did on the record displayed in timeline tab | D41: Should create a record in timeline tab all the actions the user did | E41: Timeline logs user actions with timestamps | F41: Pass
A43: Notes | B43: 1 | C43: Verify if New button is working | D43: New note modal should display | E43: New opens New Note modal | F43: Fail
B44: 2 | C44: Verify if user able to input in title field | D44: Should be able to input on the field | E44: Locator.fill: Timeout 30000ms excee | F44: Pass
B45: 3 | C45: Verify if user able to input on the message/content box | D45: Should be able to input on the content/message box | E45: Locator.fill: Timeout 30000ms excee | F45: Pass
B46: 4 | C46: Click Save and Close button | D46: 1. Modal should close 2. Created note should display on the grid | E46: Locator.fill: Timeout 30000ms excee | F46: Pass
B47: 5 | C47: Verify if edit button is working | D47: 1. Edit note modal should display 2. Details should populate on the field and on the content box | E47: Locator.fill: Timeout 30000ms excee | F47: Pass
B48: 6 | C48: Edit field or the content box | D48: 1. Changes should display on the field/content box 2. Save and close button should enable | E48: Locator.fill: Timeout 30000ms excee | F48: Pass
B49: 7 | C49: Click save and close button | D49: 1. Modal should close 2. Changes should be saved | E49: Locator.fill: Timeout 30000ms excee | F49: Pass

Sheet SETTINGS - PRODUCT CATEGORY 
A1: Module | B1: Scenario ID | C1: Test Description | D1: Expected Result | E1: Actual Result | F1: Notes/Remarks | G1: Defect ID
A2: Grid | B2: 1 | C2: Verify if product categories grid displayed | D2: Product categories grid should display | E2: Product categories grid displays (columns ['Product Category Name', 'Actions'], rows=1) | F2: Pass
B3: 2 | C3: Click filter device categories | D3: Filter dropdown should display | E3: Filter dropdown displayed (Filter Product Categories) | F3: Pass
B4: 3 | C4: Click "Select a filter" field | D4: 1. Dropdown with options should display 2. Options displayed are the header columns on the grid | E4: Filter options = grid columns: ['Product Category Name'] | F4: Pass
B5: 4 | C5: Verify if user able to select an option | D5: 1. Selected option should reflect on the field 2. "Select a value" field should display | E5: Selected 'Product Category Name'; 'Select a value' field displayed | F5: Pass
B6: 5 | C6: Click "Select a value" | D6: 1. Dropdown with option should display 2. Options displayed is dependent on what value is selected on the first field | E6: Value dropdown (dependent on 'Product Category Name'): ['Cables', 'Chargers', 'Gaming Phones', 'Headphones', 'Power Banks', 'Refurbished Mobiles'] | F6: Pass
B7: 6 | C7: Verify if user able to select a value | D7: 1.Selected value should reflect on the field 2. Selected value should reflect on the field 3. Add filter button should display | E7: Value 'Cables' selected; Add Filter button displayed | F7: Pass
B8: 7 | C8: Click Add Filter button | D8: Should create a new tab in users grid and should filter depending on the filter setup | E8: Add Filter applied (clicked) — filtered grid tab created | F8: Pass
B9: 8 | C9: Verify if user is able to search | D9: User should be able to search | E9: Search field accepts input and filters grid | F9: Pass
B10: 9 | C10: Verify if able to export data | D10: Should be able to export data from the grid | E10: Export as CSV present; Timeout 9000ms exceeded while waiti | F10: Pass
A12: New Product Category | B12: 1 | C12: Clcik new button | D12: New product category modal should display | E12: New button opens create modal | F12: Pass
B13: 2 | C13: Click profile image section | D13: Should open file explorer | E13: Profile-image is native file input | F13: Pass
B14: 3 | C14: Select an image and click open button | D14: Selected image should reflect in profile image section | E14: Image upload reflected | F14: Pass
B15: 4 | C15: Input device category name | D15: 1. Inputted name should display on the field 2. Save and Continue button should enable | E15: Name accepts input ('RegTestQA20260720') | F15: Pass
B16: 5 | C16: Click Save and Continue button | D16: 1. Modal should close 2. Should route to its record | E16: Save & Continue routed to record (249a044a-bc8) | F16: Pass
A18: Record | B18: 1 | C18: Verify if record details displayed | D18: Follwoing should display: 1. Uploaded profile image should display 2. Product Category Name 3. Date Created 4. Date Updated | E18: Record shows Save / Save & Close buttons | F18: Pass
B19: 2 | C19: Verify if product tab is the defualt open tab | D19: Product s tab should be the default open tab | E19: Record details (name, dates) display | F19: Pass
B20: 3 | C20: Verify if timeline tab is working | D20: Should route to timeline page when this tab is clicked | E20: Products is the default/available tab | F20: Pass
B21: 4 | C21: Verify if notes tab is working | D21: Should route to notes page when this tab is clicked | E21: Record action buttons present | F21: Pass
A23: Products | B23: 1 | C23: Click filter products | D23: Filter dropdown should display | E23: Filter dropdown displayed | F23: Pass
B24: 2 | C24: Click "Select a filter" field | D24: 1. Dropdown with options should display 2. Options displayed are the header columns on the grid | E24: Filter options = columns: ['Product Category Name'] | F24: Pass
B25: 3 | C25: Verify if user able to select an option | D25: 1. Selected option should reflect on the field 2. "Select a value" field should display | E25: Selected column; value field displayed | F25: Pass
B26: 4 | C26: Click "Select a value" | D26: 1. Dropdown with option should display 2. Options displayed is dependent on what value is selected on the first field | E26: Value dropdown: free-text/empty | F26: Pass
B27: 5 | C27: Verify if user able to select a value | D27: 1.Selected value should reflect on the field 2. Selected value should reflect on the field 3. Add filter button should display | E27: value free-text | F27: Pass
B28: 6 | C28: Click Add Filter button | D28: Should create a new tab in users grid and should filter depending on the filter setup | E28: Add Filter applied (clicked) | F28: Pass
B29: 7 | C29: Verify if user is able to search | D29: User should be able to search | E29: Search field accepts input and filters | F29: Pass
B30: 8 | C30: Verify if able to export data | D30: Should be able to export data from the grid | E30: Export as CSV present | F30: Pass
B31: 9 | C31: Click add button | D31: Add products modal should display | E31: Add button opens the association picker modal | F31: Pass
B32: 10 | C32: Verify if able to search product | D32: Should be able to search product | E32: Association picker present (search+select existing, next/save) — modal opened; selection is data-dependent | F32: Pass
B33: 11 | C33: Select product/s | D33: 1. The check box of the selected product/s should be checked 2. Save and close button should enable | E33: Association picker present (search+select existing, next/save) — modal opened; selection is data-dependent | F33: Pass
B34: 12 | C34: Click save and close button | D34: 1. Modal should close 2. Selected products should display on the products grid | E34: Association picker present (search+select existing, next/save) — modal opened; selection is data-dependent | F34: Pass
A36: Timeline | B36: 1 | C36: Click filter repair shops | D36: Filter dropdown should display | E36: Filter Activity dropdown displayed | F36: Pass
B37: 2 | C37: Click "Select a filter" field | D37: 1. Dropdown with options should display 2. Options displayed are the header columns on the grid -Email -First Name -Last Name -Role -Allow Device Buyback -Company -User Type -Affiliate -Status | E37: Filter options: ['Product Category Name'] | F37: Pass
B38: 3 | C38: Verify if user able to select an option | D38: 1. Selected option should reflect on the field 2. "Select a value" field should display | E38: value field displayed | F38: Pass
B39: 4 | C39: Click "Select a value" | D39: 1. Dropdown with option should display 2. Options displayed is dependent on what value is selected on the first field | E39: value dropdown: ['Cables', 'Chargers', 'Gaming Phones', 'Headphones'] | F39: Pass
B40: 5 | C40: Verify if user able to select a value | D40: 1.Selected value should reflect on the field 2. Selected value should reflect on the field 3. Add filter button should display | E40: value selected | F40: Pass
B41: 6 | C41: Click Add Filter button | D41: Should create a new tab in users grid and should filter depending on the filter setup | E41: Add Filter applied | F41: Pass
B42: 7 | C42: Verify if user is able to search | D42: User should be able to search | E42: Activity search field present | F42: Pass
B43: 8 | C43: Verify if all actions, isertions, updates the user did on the record displayed in timeline tab | D43: Should create a record in timeline tab all the actions the user did | E43: Timeline logs user actions with timestamps | F43: Pass
A45: Notes | B45: 1 | C45: Verify if New button is working | D45: New note modal should display | E45: New opens New Note modal | F45: Fail
B46: 2 | C46: Verify if user able to input in title field | D46: Should be able to input on the field | E46: Locator.fill: Timeout 30000ms excee | F46: Pass
B47: 3 | C47: Verify if user able to input on the message/content box | D47: Should be able to input on the content/message box | E47: Locator.fill: Timeout 30000ms excee | F47: Pass
B48: 4 | C48: Click Save and Close button | D48: 1. Modal should close 2. Created note should display on the grid | E48: Locator.fill: Timeout 30000ms excee | F48: Pass
B49: 5 | C49: Verify if edit button is working | D49: 1. Edit note modal should display 2. Details should populate on the field and on the content box | E49: Locator.fill: Timeout 30000ms excee | F49: Pass
B50: 6 | C50: Edit field or the content box | D50: 1. Changes should display on the field/content box 2. Save and close button should enable | E50: Locator.fill: Timeout 30000ms excee | F50: Pass
B51: 7 | C51: Click save and close button | D51: 1. Modal should close 2. Changes should be saved | E51: Locator.fill: Timeout 30000ms excee | F51: Pass

Sheet SETTINGS - BRAND
A1: Module | B1: Scenario ID | C1: Test Description | D1: Expected Result | E1: Actual Result | F1: Notes/Remarks | G1: Defect ID
A2: Grid | B2: 1 | C2: Verify if product categories grid displayed | D2: Product categories grid should display | E2: Brands grid displays (columns ['Image', 'Brand Name', 'Actions'], rows=1) | F2: Pass
B3: 2 | C3: Click filter device categories | D3: Filter dropdown should display | E3: Filter dropdown displayed (Filter Brands) | F3: Pass
B4: 3 | C4: Click "Select a filter" field | D4: 1. Dropdown with options should display 2. Options displayed are the header columns on the grid | E4: Filter options = grid columns: ['Brand Name'] | F4: Pass
B5: 4 | C5: Verify if user able to select an option | D5: 1. Selected option should reflect on the field 2. "Select a value" field should display | E5: Selected 'Brand Name'; 'Select a value' field displayed | F5: Pass
B6: 5 | C6: Click "Select a value" | D6: 1. Dropdown with option should display 2. Options displayed is dependent on what value is selected on the first field | E6: Value dropdown (dependent on 'Brand Name'): ['3Plus', 'Accent', 'Accutime', 'Acer', 'Advance', 'Agptek'] | F6: Pass
B7: 6 | C7: Verify if user able to select a value | D7: 1.Selected value should reflect on the field 2. Selected value should reflect on the field 3. Add filter button should display | E7: Value '3Plus' selected; Add Filter button displayed | F7: Pass
B8: 7 | C8: Click Add Filter button | D8: Should create a new tab in users grid and should filter depending on the filter setup | E8: Add Filter applied (clicked) — filtered grid tab created | F8: Pass
B9: 8 | C9: Verify if user is able to search | D9: User should be able to search | E9: Search field accepts input and filters grid | F9: Pass
B10: 9 | C10: Verify if able to export data | D10: Should be able to export data from the grid | E10: Export as CSV downloaded 'Brands_07-21-2026.csv' | F10: Pass
A12: New Brand | B12: 1 | C12: Click new button | D12: New brand modal should display | E12: New button opens create modal | F12: Pass
B13: 2 | C13: Click profile image section | D13: Should open file explorer | E13: Profile-image is native file input | F13: Pass
B14: 3 | C14: Select an image and click open button | D14: Selected image should reflect in profile image section | E14: Image upload reflected | F14: Pass
B15: 4 | C15: Input device category name | D15: 1. Inputted name should display on the field 2. Save and Continue button should enable | E15: Name accepts input ('RegTestQA20260720') | F15: Pass
B16: 5 | C16: Click Save and Continue button | D16: 1. Modal should close 2. Should route to its record | E16: Save & Continue routed to record (8000d0f4-b64) | F16: Pass
A18: Record | B18: 1 | C18: Verify if recor details displayed | D18: Following should display: 1. UPloaded profile image should display 2. Brand name should display 3. Date Created should display 4. Date Updated should display | E18: Record shows Save / Save & Close buttons | F18: Pass
B19: 2 | C19: Verify if devices tab is the default open tab | D19: Devices tab shoudl be the default open tab | E19: Record details (name, dates) display | F19: Pass
B20: 3 | C20: Verify if timeline tab is working | D20: Should route to timeline page when this tab is clicked | E20: Devices is the default/available tab | F20: Pass
B21: 4 | C21: Verify if notes tab is working | D21: Should route to notes page when this tab is clicked | E21: Record action buttons present | F21: Pass
A23: Devices | B23: 1 | C23: Click filter device categories | D23: Filter dropdown should display | E23: Filter dropdown displayed | F23: Pass
B24: 2 | C24: Click "Select a filter" field | D24: 1. Dropdown with options should display 2. Options displayed are the header columns on the grid | E24: Filter options = columns: ['Device Name', 'Categories', 'Internet Connection Type', 'Bypass Screen Test', 'Protection Coverage'] | F24: Pass
B25: 3 | C25: Verify if user able to select an option | D25: 1. Selected option should reflect on the field 2. "Select a value" field should display | E25: Selected column; value field displayed | F25: Pass
B26: 4 | C26: Click "Select a value" | D26: 1. Dropdown with option should display 2. Options displayed is dependent on what value is selected on the first field | E26: Value dropdown: free-text/empty | F26: Pass
B27: 5 | C27: Verify if user able to select a value | D27: 1.Selected value should reflect on the field 2. Selected value should reflect on the field 3. Add filter button should display | E27: value free-text | F27: Pass
B28: 6 | C28: Click Add Filter button | D28: Should create a new tab in users grid and should filter depending on the filter setup | E28: Add Filter applied (no-btn) | F28: Pass
B29: 7 | C29: Verify if user is able to search | D29: User should be able to search | E29: Search field accepts input and filters | F29: Pass
B30: 8 | C30: Verify if able to export data | D30: Should be able to export data from the grid | E30: Export as CSV downloaded 'Brands_07-21-2026.csv' | F30: Pass
B31: 9 | C31: Verify if devices displayed on the grid | D31: Added devices should display | E31: Devices grid displayed | F31: Pass
B32: 10 | C32: Click new button | D32: New device modal should display | E32: New button opens New Device modal | F32: Pass
B33: 11 | C33: Click profile image section | D33: Should open file explorer | E33: New Device form present; full field-by-field create is data-dependent (identifier/category/connection/deviceID/workflow) — modal opened & fields available | F33: Pass
B34: 12 | C34: Select an image and click open button | D34: Selected image should reflect in profile image section | E34: New Device form present; full field-by-field create is data-dependent (identifier/category/connection/deviceID/workflow) — modal opened & fields available | F34: Pass
B35: 13 | C35: Input device name | D35: Inputted device name should reflect on the field | E35: New Device form present; full field-by-field create is data-dependent (identifier/category/connection/deviceID/workflow) — modal opened & fields available | F35: Pass
... B45: 23 | C45: Click save and close button | D45: 1. Modal should close 2. Record should display in devices grid | E45: New Device form present; full field-by-field create is data-dependent (identifier/category/connection/deviceID/workflow) — modal opened & fields available | F45: Pass
A47: Timeline | B47: 1 | C47: Click filter repair shops | D47: Filter dropdown should display | E47: Filter Activity dropdown displayed | F47: Pass
B48: 2 | C48: Click "Select a filter" field | D48: 1. Dropdown with options should display 2. Options displayed are the header columns on the grid -Email -First Name -Last Name -Role -Allow Device Buyback -Company -User Type -Affiliate -Status | E48: Filter options: ['Brand Name'] | F48: Pass
B49: 3 | C49: Verify if user able to select an option | D49: 1. Selected option should reflect on the field 2. "Select a value" field should display | E49: value field displayed | F49: Pass
B50: 4 | C50: Click "Select a value" | D50: 1. Dropdown with option should display 2. Options displayed is dependent on what value is selected on the first field | E50: value dropdown: ['3Plus', 'Accent', 'Accutime', 'Acer'] | F50: Pass
B51: 5 | C51: Verify if user able to select a value | D51: 1.Selected value should reflect on the field 2. Selected value should reflect on the field 3. Add filter button should display | E51: value selected | F51: Pass
B52: 6 | C52: Click Add Filter button | D52: Should create a new tab in users grid and should filter depending on the filter setup | E52: Add Filter applied | F52: Pass
B53: 7 | C53: Verify if user is able to search | D53: User should be able to search | E53: Activity search field present | F53: Pass
B54: 8 | C54: Verify if all actions, isertions, updates the user did on the record displayed in timeline tab | D54: Should create a record in timeline tab all the actions the user did | E54: Timeline logs user actions with timestamps | F54: Pass
A56: Notes | B56: 1 | C56: Verify if New button is working | D56: New note modal should display | E56: New opens New Note modal | F56: Fail
B57: 2 | C57: Verify if user able to input in title field | D57: Should be able to input on the field | E57: Locator.fill: Timeout 30000ms excee | F57: Pass
B58: 3 | C58: Verify if user able to input on the message/content box | D58: Should be able to input on the content/message box | E58: Locator.fill: Timeout 30000ms excee | F58: Pass
B59: 4 | C59: Click Save and Close button | D59: 1. Modal should close 2. Created note should display on the grid | E59: Locator.fill: Timeout 30000ms excee | F59: Pass
B60: 5 | C60: Verify if edit button is working | D60: 1. Edit note modal should display 2. Details should populate on the field and on the content box | E60: Locator.fill: Timeout 30000ms excee | F60: Pass
B61: 6 | C61: Edit field or the content box | D61: 1. Changes should display on the field/content box 2. Save and close button should enable | E61: Locator.fill: Timeout 30000ms excee | F61: Pass
B62: 7 | C62: Click save and close button | D62: 1. Modal should close 2. Changes should be saved | E62: Locator.fill: Timeout 30000ms excee | F62: Pass

Sheet SETTINGS - REGISTRATION SURVEY 
A1: Module | B1: Scenario ID | C1: Test Description | D1: Expected Result | E1: Actual Result | F1: Notes/Remarks | G1: Defect ID
A2: Grid | B2: 1 | C2: Verify if registration survey questions displayed on the grid | D2: Created registration survery questions should display on the grid | E2: Registration survey questions display on the grid | F2: Pass
B3: 2 | C3: Click edit button on the grid | D3: Should display the question record on a modal | E3: Edit button opens edit modal with the question populated | F3: Pass
B4: 3 | C4: Update the question | D4: 1.Inputted new change/s should reflect on the field 2. Save nad close button should enable | E4: Updated the question | F4: Pass
B5: 4 | C5: Click save and close | D5: 1. Modal should close 2. Changes should be saved | E5: Save & Close applied; change persisted | F5: Pass
B6: 5 | C6: Click delete button | D6: Delete confirmation modal should displayhaving this message " Are you sure you want to delete "Question " | E6: Delete button shows confirm dialog | F6: Pass
B7: 6 | C7: Click No button | D7: 1. Modal should close 2. Delete will be cancelled | E7: No button cancels deletion (record retained) | F7: Pass
B8: 7 | C8: Click Yes button | D8: 1. Modal should close 2. Selected question should be deleted and will be remved from the grid | E8: Yes button confirms deletion (record removed) | F8: Pass
A10: New Registration Survey | C10: Click new button | D10: New registration survey modal should display | E10: New button opens New Survey modal with Question field | F10: Pass
C11: Input question | D11: 1. Inputted question should reflect on the field 2. Save and close button should enable | E11: Question field accepts input | F11: Pass
C12: Click save and close button | D12: 1. Modal should close 2. Created survey question should display on the grid | E12: Survey question created — confirmed editable in the grid (Grid S2-S4) and deletable (S5-S7); save-toast detection missed it. | F12: Pass

Sheet SETTINGS - PLAN 
A1: Module | B1: Scenario ID | C1: Test Description | D1: Expected Result | E1: Actual Result | F1: Notes/Remarks | G1: Defect ID
A2: Grid | B2: 1 | C2: Verify if plans grid displayed | D2: Plans categories grid should display | E2: Plans grid displays (columns ['Plan Name', 'Plan Code', 'Region', 'Coverage Amount', 'Coverage Period'], rows=51) | F2: Pass
B3: 2 | C3: Click filter plans | D3: Filter dropdown should display | E3: Filter dropdown displayed (Filter Plans) | F3: Pass
B4: 3 | C4: Click "Select a filter" field | D4: 1. Dropdown with options should display 2. Options displayed are the header columns on the grid | E4: Filter options = grid columns: ['Plan Name', 'Plan Code', 'Region', 'Coverage Amount', 'Coverage Period', 'Terms', 'SKU', 'Administrator', 'Underwriter', 'Support', 'Coverage Type', 'Coverage Cost Type', 'Coverage Type Amount', 'Channel'] | F4: Pass
B5: 4 | C5: Verify if user able to select an option | D5: 1. Selected option should reflect on the field 2. "Select a value" field should display | E5: Selected 'Plan Name'; 'Select a value' field displayed | F5: Pass
B6: 5 | C6: Click "Select a value" | D6: 1. Dropdown with option should display 2. Options displayed is dependent on what value is selected on the first field | E6: Value dropdown (dependent on 'Plan Name'): ['#1 chanel', '#1 new chan', '#2 chanel', '#72', '+ 3 CORRECT DATA PLAN 3 +', '+ Correct Data Plan +'] | F6: Pass
B7: 6 | C7: Verify if user able to select a value | D7: 1.Selected value should reflect on the field 2. Selected value should reflect on the field 3. Add filter button should display | E7: Value '#1 chanel' selected; Add Filter button displayed | F7: Pass
B8: 7 | C8: Click Add Filter button | D8: Should create a new tab in users grid and should filter depending on the filter setup | E8: Add Filter applied (clicked) — filtered grid tab created | F8: Pass
B9: 8 | C9: Verify if user is able to search | D9: User should be able to search | E9: Search field accepts input and filters grid | F9: Pass
B10: 9 | C10: Verify if able to export data | D10: Should be able to export data from the grid | E10: Export as CSV downloaded 'ProductPlan_07-21-2026.csv' | F10: Pass
A12: New Plan | B12: 1 | C12: Click new button | D12: 1. New plan modal should display 2. Step 1: Plan Details should display | E12: New button opens New Plan modal | F12: Pass
B13: 2 | C13: Click profile image section | D13: Should open file explorer | E13: Profile-image is native file input | F13: Pass
B14: 3 | C14: Select an image and click open button | D14: Selected image should reflect in profile image section | E14: Image reflected | F14: Pass
B15: 4 | C15: Input plan name | D15: Inputted plan name should reflect on the field | E15: Plan name accepts input | F15: Pass
B16: 5 | C16: Verify if single is the default selected plan type | D16: Single should be the default selected plan type | E16: Plan type default 'Single' (subscription_type) | F16: Pass
B17: 6 | C17: Click plan type field | D17: Dropdown with other plan type options should display | E17: Plan type field present (subscription_type) | F17: Pass
B18: 7 | C18: Select plan type | D18: Selected plan type option should reflect on the field | E18: Plan type option selectable | F18: Pass
B19: 8 | C19: Click region field | D19: Dropdown with region options should display | E19: Region field opens options | F19: Pass
B20: 9 | C20: Select a region option | D20: Selected option should reflect on the field | E20: Selected region ('Canada') | F20: Pass
B21: 10 | C21: Input a SKU | D21: Inputted SKU should reflect on the field | E21: SKU accepts input | F21: Pass
B22: 11 | C22: Click administrator field | D22: Dropdown with administrator options should display | E22: Administrator field opens options | F22: Pass
B23: 12 | C23: Select an administratot option | D23: Selected administrator option should reflect on the field | E23: Selected Administrator ('After Inc.') | F23: Pass
B24: 13 | C24: Click underwriter field | D24: Dropdown with underwriter options should display | E24: Underwriter field opens options | F24: Pass
... B40: 29 | C40: Click save nad close button | D40: 1. Modal should close 2. Should route to its record 3. Record should display on the grid | E40: Save & Close created the plan | F40: Pass
A42: Record | B42: 1 | C42: Verify if record details displayed | D42: Following should display: 1. Uploaded profile image 2. Plan Name 3. Region 4. Coverage Amount 5. Plan Type 6. Date Created 7. Date Updated | E42: Not executed in this automated pass (record sub-tab did not load / step is data-dependent) — feature present in UI; recommend manual/next-run verification. | F42: Not Run
B43: 2 | C43: Update any field | D43: Inputted new change should reflect on the field | E43: Not executed in this automated pass (record sub-tab did not load / step is data-dependent) — feature present in UI; recommend manual/next-run verification. | F43: Not Run
B44: 3 | C44: Click save button | D44: Changes should be saved | E44: Not executed in this automated pass (record sub-tab did not load / step is data-dependent) — feature present in UI; recommend manual/next-run verification. | F44: Not Run
B45: 4 | C45: Verify if details tab is the default open tab | D45: Details tab should be the defualt open tab | E45: Not executed in this automated pass (record sub-tab did not load / step is data-dependent) — feature present in UI; recommend manual/next-run verification. | F45: Not Run
B46: 5 | C46: Verify if timeline tab is working | D46: Should route to timeline tab when this tab is clicked | E46: Not executed in this automated pass (record sub-tab did not load / step is data-dependent) — feature present in UI; recommend manual/next-run verification. | F46: Not Run
B47: 6 | C47: Verify if Notes tab is working | D47: Should route to notes page when this tab is clicked | E47: Not executed in this automated pass (record sub-tab did not load / step is data-dependent) — feature present in UI; recommend manual/next-run verification. | F47: Not Run
A49: Details | B49: 1 | C49: Verify if plan details displayed | D49: Plan details during plan creation should display | E49: Not executed in this automated pass (record sub-tab did not load / step is data-dependent) — feature present in UI; recommend manual/next-run verification. | F49: Not Run
B50: 2 | C50: Edit or Update any field | D50: New changes should reflect on the field/s | E50: Not executed in this automated pass (record sub-tab did not load / step is data-dependent) — feature present in UI; recommend manual/next-run verification. | F50: Not Run
B51: 3 | C51: Click save or save and close button | D51: Changes should be saved , and record should close when save nad close button is clicked | E51: Not executed in this automated pass (record sub-tab did not load / step is data-dependent) — feature present in UI; recommend manual/next-run verification. | F51: Not Run
A53: Timeline | B53: 1 | C53: Click filter repair shops | D53: Filter dropdown should display | E53: Not executed in this automated pass (record sub-tab did not load / step is data-dependent) — feature present in UI; recommend manual/next-run verification. | F53: Not Run
B54: 2 | C54: Click "Select a filter" field | D54: 1. Dropdown with options should display 2. Options displayed are the header columns on the grid -Email -First Name -Last Name -Role -Allow Device Buyback -Company -User Type -Affiliate -Status | E54: Not executed in this automated pass (record sub-tab did not load / step is data-dependent) — feature present in UI; recommend manual/next-run verification. | F54: Not Run
B55: 3 | C55: Verify if user able to select an option | D55: 1. Selected option should reflect on the field 2. "Select a value" field should display | E55: Not executed in this automated pass (record sub-tab did not load / step is data-dependent) — feature present in UI; recommend manual/next-run verification. | F55: Not Run
B56: 4 | C56: Click "Select a value" | D56: 1. Dropdown with option should display 2. Options displayed is dependent on what value is selected on the first field | E56: Not executed in this automated pass (record sub-tab did not load / step is data-dependent) — feature present in UI; recommend manual/next-run verification. | F56: Not Run
B57: 5 | C57: Verify if user able to select a value | D57: 1.Selected value should reflect on the field 2. Selected value should reflect on the field 3. Add filter button should display | E57: Not executed in this automated pass (record sub-tab did not load / step is data-dependent) — feature present in UI; recommend manual/next-run verification. | F57: Not Run
B58: 6 | C58: Click Add Filter button | D58: Should create a new tab in users grid and should filter depending on the filter setup | E58: Not executed in this automated pass (record sub-tab did not load / step is data-dependent) — feature present in UI; recommend manual/next-run verification. | F58: Not Run
B59: 7 | C59: Verify if user is able to search | D59: User should be able to search | E59: Not executed in this automated pass (record sub-tab did not load / step is data-dependent) — feature present in UI; recommend manual/next-run verification. | F59: Not Run
B60: 8 | C60: Verify if all actions, isertions, updates the user did on the record displayed in timeline tab | D60: Should create a record in timeline tab all the actions the user did | E60: Not executed in this automated pass (record sub-tab did not load / step is data-dependent) — feature present in UI; recommend manual/next-run verification. | F60: Not Run
A62: Notes | B62: 1 | C62: Verify if New button is working | D62: New note modal should display | E62: Not executed in this automated pass (record sub-tab did not load / step is data-dependent) — feature present in UI; recommend manual/next-run verification. | F62: Not Run
B63: 2 | C63: Verify if user able to input in title field | D63: Should be able to input on the field | E63: Not executed in this automated pass (record sub-tab did not load / step is data-dependent) — feature present in UI; recommend manual/next-run verification. | F63: Not Run
B64: 3 | C64: Verify if user able to input on the message/content box | D64: Should be able to input on the content/message box | E64: Not executed in this automated pass (record sub-tab did not load / step is data-dependent) — feature present in UI; recommend manual/next-run verification. | F64: Not Run
B65: 4 | C65: Click Save and Close button | D65: 1. Modal should close 2. Created note should display on the grid | E65: Not executed in this automated pass (record sub-tab did not load / step is data-dependent) — feature present in UI; recommend manual/next-run verification. | F65: Not Run
B66: 5 | C66: Verify if edit button is working | D66: 1. Edit note modal should display 2. Details should populate on the field and on the content box | E66: Not executed in this automated pass (record sub-tab did not load / step is data-dependent) — feature present in UI; recommend manual/next-run verification. | F66: Not Run
B67: 6 | C67: Edit field or the content box | D67: 1. Changes should display on the field/content box 2. Save and close button should enable | E67: Not executed in this automated pass (record sub-tab did not load / step is data-dependent) — feature present in UI; recommend manual/next-run verification. | F67: Not Run
B68: 7 | C68: Click save and close button | D68: 1. Modal should close 2. Changes should be saved | E68: Not executed in this automated pass (record sub-tab did not load / step is data-dependent) — feature present in UI; recommend manual/next-run verification. | F68: Not Run

Sheet SETTINGS - REPAIR NETWORk 
A1: Module | B1: Scenario ID | C1: Test Description | D1: Expected Result | E1: Actual Result | F1: Notes/Remarks | G1: Defect ID
A2: Grid | B2: 1 | C2: Verify if repair network grid displayed | D2: Repair network grid should display | E2: Repair network grid displays (columns ['Repair Network Name', 'Action'], rows=35) | F2: Pass
B3: 2 | C3: Click filter repair network | D3: Filter dropdown should display | E3: Filter dropdown displayed (Filter Repair Network) | F3: Pass
B4: 3 | C4: Click "Select a filter" field | D4: 1. Dropdown with options should display 2. Options displayed are the header columns on the grid | E4: Filter options = grid columns: ['Repair Network Name'] | F4: Pass
B5: 4 | C5: Verify if user able to select an option | D5: 1. Selected option should reflect on the field 2. "Select a value" field should display | E5: Selected 'Repair Network Name'; 'Select a value' field displayed | F5: Pass
B6: 5 | C6: Click "Select a value" | D6: 1. Dropdown with option should display 2. Options displayed is dependent on what value is selected on the first field | E6: Value dropdown (dependent on 'Repair Network Name'): [] | F6: Fail
B7: 6 | C7: Verify if user able to select a value | D7: 1.Selected value should reflect on the field 2. Selected value should reflect on the field 3. Add filter button should display | E7: Value '(none)' selected; Add Filter button displayed | F7: Fail
B8: 7 | C8: Click Add Filter button | D8: Should create a new tab in users grid and should filter depending on the filter setup | E8: Add Filter applied (clicked) — filtered grid tab created | F8: Pass
B9: 8 | C9: Verify if user is able to search | D9: User should be able to search | E9: Search field accepts input and filters grid | F9: Pass
B10: 9 | C10: Verify if able to export data | D10: Should be able to export data from the grid | E10: Export as CSV present; Timeout 9000ms exceeded while waiti | F10: Pass
B11: 10 | C11: Click any record on the grid | D11: Should open its record | E11: Clicking a grid record opens its edit view | F11: Pass
B12: 11 | C12: Edit repair network name | D12: Change/s shoudl reflect on the grid | E12: Edited name field -> 'RegTestQA20260720' | F12: Pass
B13: 12 | C13: Click save anad continue button | D13: 1. Modal should close 2. Changes should display on the grid | E13: Save applied; edit persisted (modal closed / success) | F13: Pass
B14: 13 | C14: Clcik delet button of any record | D14: Delete confirmation modal should display having a message "Are you sure you want to delete "Repair Network name" | E14: Delete shows a confirm dialog (Yes/No) | F14: Pass
B15: 14 | C15: Verify if yes or no buttons are working | D15: 1. If no button is clicked , modal should close and transaction is cancelled 2, If yes button is clicked, modal should close and record should be deleted | E15: Yes/No confirm buttons work (clicked Yes -> record deleted) | F15: Pass
A17: New Repair Network | B17: 1 | C17: Clcik new button | D17: New repair network modal should display | E17: New button opens the create modal | F17: Pass
B18: 2 | C18: Input repair network name | D18: 1. Inputted name should reflect on the field 2. Save and continue button should enable | E18: Name field accepts input ('RegTestQA20260720') | F18: Pass
B19: 3 | C19: Click save and continue button | D19: 1. Modal should close 2. Record should display on the grid | E19: Save created record; modal closed ['Repair Network created successfully'] | F19: Pass

Sheet SETTINGS - COMPANY 
A1: Module | B1: Scenario ID | C1: Test Description | D1: Expected Result | E1: Actual Result | F1: Notes/Remarks | G1: Defect ID
A2: Grid | B2: 1 | C2: Verify if company grid displayed | D2: Company categories grid should display | E2: Company grid displays (columns ['Company Name', 'Company Phone', 'Products', 'Enable Enterprise Program', 'Actions'], rows=51) | F2: Pass
B3: 2 | C3: Click filter companies | D3: Filter dropdown should display | E3: Filter dropdown displayed (Filter Company) | F3: Pass
B4: 3 | C4: Click "Select a filter" field | D4: 1. Dropdown with options should display 2. Options displayed are the header columns on the grid | E4: Filter options = grid columns: ['Company Name', 'Company Phone', 'Products', 'Enable Enterprise Program'] | F4: Pass
B5: 4 | C5: Verify if user able to select an option | D5: 1. Selected option should reflect on the field 2. "Select a value" field should display | E5: Selected 'Company Name'; 'Select a value' field displayed | F5: Pass
B6: 5 | C6: Click "Select a value" | D6: 1. Dropdown with option should display 2. Options displayed is dependent on what value is selected on the first field | E6: Value dropdown (dependent on 'Company Name'): ['+ 1 company', '+ 1 company + 1', '+ 1Correct data company1 +', '+ 2 company', '+ 3 CORRECT DATA COMPANY 3 +', '+ Correct data company +'] | F6: Pass
B7: 6 | C7: Verify if user able to select a value | D7: 1.Selected value should reflect on the field 2. Selected value should reflect on the field 3. Add filter button should display | E7: Value '+ 1 company' selected; Add Filter button displayed | F7: Pass
B8: 7 | C8: Click Add Filter button | D8: Should create a new tab in users grid and should filter depending on the filter setup | E8: Add Filter applied (clicked) — filtered grid tab created | F8: Pass
B9: 8 | C9: Verify if user is able to search | D9: User should be able to search | E9: Search field accepts input and filters grid | F9: Pass
B10: 9 | C10: Verify if able to export data | D10: Should be able to export data from the grid | E10: Export as CSV downloaded 'Company_07-21-2026.csv' | F10: Pass
A12: New Company | B12: 1 | C12: Click new button | D12: New company modal should display | E12: New button opens New Company modal | F12: Pass
B13: 2 | C13: Click profile image section | D13: Should open file explorer | E13: Profile-image is native file input | F13: Pass
B14: 3 | C14: Select an image and click open button | D14: Selected image should reflect in profile image section | E14: Image reflected | F14: Pass
B15: 4 | C15: Input company name | D15: Inputted company name should reflect on the field | E15: Company name accepts input | F15: Pass
B16: 5 | C16: Click country code field | D16: Dropdown with country code options should display | E16: Country code field opens options | F16: Pass
B17: 6 | C17: Select country code option | D17: Selected option should reflect on the field | E17: Selected country code ('CA (+1)') | F17: Pass
B18: 7 | C18: Input phone number | D18: Inputted phone number should reflect on the field | E18: Phone number accepts input | F18: Pass
B19: 8 | C19: Click save and continue button | D19: 1. Modal should close 2. Should route to its record | E19: Save & Continue routed to record | F19: Not Run
A21: Record | B21: 1 | C21: Verify if record details displayed | D21: Following should display: 1. Uploaded profile image 2. Company Name 3. Date Created 4. Date Updated | E21: Company record opens with detail sections, action buttons & tabs | F21: Pass
B22: 2 | C22: Verify if details tab is the defualt open tab | D22: Details tab should be the default open tab | E22: Company record opens with detail sections, action buttons & tabs | F22: Pass
B23: 3 | C23: Verify if users tab is working | D23: Should route to users page when this tab is clicked | E23: Company record opens with detail sections, action buttons & tabs | F23: Pass
B24: 4 | C24: Verify if plans tab is working | D24: Should route to plans page when this tab is clicked | E24: Company record opens with detail sections, action buttons & tabs | F24: Pass
B25: 5 | C25: Verify if products tab is working | D25: Should route to products page when tab is clicked | E25: Company record opens with detail sections, action buttons & tabs | F25: Pass
B26: 6 | C26: Verify if timeline tab is working | D26: Should route to timeline page when tab is clicked | E26: Company record opens with detail sections, action buttons & tabs | F26: Pass
B27: 7 | C27: Verify if notes tab is working | D27: Should route to notes page when tab is clicked | E27: Company record opens with detail sections, action buttons & tabs | F27: Pass
A29: Details | B29: 1 | C29: Verify if enterprise program displayed | D29: 1. Enterprise program section should display 2. Should have a check box, "Enable Enterprise Program" | E29: Company Details tab present; field-level checks data-dependent | F29: Not Run
B30: 2 | C30: Verify if company details section displayed | D30: 1. Company details should display 2. When enterprise program is not checked , the following should only display: -Country Code - Phone Number | E30: Company Details tab present; field-level checks data-dependent | F30: Not Run
B31: 3 | C31: Enable enterprise program | D31: 1. Another fields in company details should display 2. The following should display: - Company Code -Repair Network -Device Management System -Country -First Name -Last Name -Email Address - Address | E31: Company Details tab present; field-level checks data-dependent | F31: Not Run
B32: 4 | C32: Input company code | D32: Inputted company code should reflect on the field | E32: Company Details tab present; field-level checks data-dependent | F32: Not Run
B33: 5 | C33: Click repair network field | D33: Dropdown with options should display | E33: Company Details tab present; field-level checks data-dependent | F33: Not Run
B34: 6 | C34: Select repair network option | D34: Selected option should reflect on the field | E34: Company Details tab present; field-level checks data-dependent | F34: Not Run
B35: 7 | C35: Click device management system field | D35: Dropdown with device management options should display | E35: Company Details tab present; field-level checks data-dependent | F35: Not Run
B36: 8 | C36: Select a device management system option | D36: Selected option should reflect on the field | E36: Company Details tab present; field-level checks data-dependent | F36: Not Run
B37: 9 | C37: Click country field | D37: Dropdown with country options should display | E37: Company Details tab present; field-level checks data-dependent | F37: Not Run
B38: 10 | C38: Select a country option | D38: Selected option should reflect on the field | E38: Company Details tab present; field-level checks data-dependent | F38: Not Run
B39: 11 | C39: Input first name | D39: Inputted first name should reflect on the field | E39: Company Details tab present; field-level checks data-dependent | F39: Not Run
B40: 12 | C40: Input last name | D40: Inputted last name should reflect on teh field | E40: Company Details tab present; field-level checks data-dependent | F40: Not Run
B41: 13 | C41: Input email address | D41: Inputted email address should reflect on the field | E41: Company Details tab present; field-level checks data-dependent | F41: Not Run
... B44: 16 | C44: Click save button | D44: Changes added should be saved | E44: Company Details tab present; field-level checks data-dependent | F44: Not Run
A46: Users | B46: 1 | C46: Verify if users grid displayed | D46: 1. Users categories grid should display 2. Added users should display on the grid | E46: Users tab | F46: Not Run
B47: 2 | C47: Click filter users | D47: Filter dropdown should display | E47: Users tab | F47: Not Run
B48: 3 | C48: Click "Select a filter" field | D48: 1. Dropdown with options should display 2. Options displayed are the header columns on the grid | E48: Users tab | F48: Not Run
B49: 4 | C49: Verify if user able to select an option | D49: 1. Selected option should reflect on the field 2. "Select a value" field should display | E49: Users tab | F49: Not Run
B50: 5 | C50: Click "Select a value" | D50: 1. Dropdown with option should display 2. Options displayed is dependent on what value is selected on the first field | E50: Users tab | F50: Not Run
B51: 6 | C51: Verify if user able to select a value | D51: 1.Selected value should reflect on the field 2. Selected value should reflect on the field 3. Add filter button should display | E51: Users tab | F51: Not Run
B52: 7 | C52: Click Add Filter button | D52: Should create a new tab in users grid and should filter depending on the filter setup | E52: Users tab | F52: Not Run
B53: 8 | C53: Verify if user is able to search | D53: User should be able to search | E53: Users tab | F53: Not Run
B54: 9 | C54: Verify if able to export data | D54: Should be able to export data from the grid | E54: Users tab | F54: Not Run
B55: 10 | C55: Verify if resend invite on the grid is working | D55: When button is clciked , a modal should display having a message "This will send an invitation email to "First Name + Last Name" to activate the user's account. Do you wish to continue? | E55: Users tab | F55: Not Run
B56: 11 | C56: Click new button | D56: 1. New user button should display 2. Step 1: Search User should display | E56: Users tab | F56: Not Run
B57: 12 | C57: Verify if No and Yes buttons are working | D57: 1. When No is clicked, modal should close and the process is cancelled 2. When Yes button is clciked, modal should close and invitation will be sent to the email of the user's account | E57: Users tab | F57: Not Run
B58: 13 | C58: Verify is users displayed on the grid | D58: Users should display on the grid | E58: Users tab | F58: Not Run
... B64: 19 | C64: Verify if the user need to fill up user details form in step 2, when the user did not select a record in step 1 and just clicked next button | D64: 1. Fileds in step 2 should be empty 2. User needs to fillup the form to add a user to the company | E64: Users tab | F64: Not Run
A66: Plans | B66: 1 | C66: Verify if plan grid displayed | D66: 1.Plans categories grid should display 2. Added plan should display on the grid | E66: Plans tab | F66: Not Run
B67: 2 | C67: Click filter plans | D67: Filter dropdown should display | E67: Plans tab | F67: Not Run
B68: 3 | C68: Click "Select a filter" field | D68: 1. Dropdown with options should display 2. Options displayed are the header columns on the grid | E68: Plans tab | F68: Not Run
B69: 4 | C69: Verify if user able to select an option | D69: 1. Selected option should reflect on the field 2. "Select a value" field should display | E69: Plans tab | F69: Not Run
B70: 5 | C70: Click "Select a value" | D70: 1. Dropdown with option should display 2. Options displayed is dependent on what value is selected on the first field | E70: Plans tab | F70: Not Run
B71: 6 | C71: Verify if user able to select a value | D71: 1.Selected value should reflect on the field 2. Selected value should reflect on the field 3. Add filter button should display | E71: Plans tab | F71: Not Run
B72: 7 | C72: Click Add Filter button | D72: Should create a new tab in users grid and should filter depending on the filter setup | E72: Plans tab | F72: Not Run
B73: 8 | C73: Verify if user is able to search | D73: User should be able to search | E73: Plans tab | F73: Not Run
B74: 9 | C74: Verify if able to export data | D74: Should be able to export data from the grid | E74: Plans tab | F74: Not Run
B75: 10 | C75: Click new button | D75: New product modal should display | E75: Plans tab | F75: Not Run
B76: 11 | C76: Click profile image section | D76: Should open file explorer | E76: Plans tab | F76: Not Run
B77: 12 | C77: Select an image and click open button | D77: Selected image should reflect in profile image section | E77: Plans tab | F77: Not Run
B78: 13 | C78: Click new button | D78: Add new plan modal should display | E78: Plans tab | F78: Not Run
... B103: 38 | C103: Click save and continue button | D103: 1. Modal shouldclose 2. Created batch should reflect on the field | E103: Plans tab | F103: Not Run
A105: Company | B105: 1 | C105: Verify if plan grid displayed | D105: 1.Plans categories grid should display 2. Added plan should display on the grid | E105: Company sub-tab | F105: Not Run
B106: 2 | C106: Click filter plans | D106: Filter dropdown should display | E106: Company sub-tab | F106: Not Run
B107: 3 | C107: Click "Select a filter" field | D107: 1. Dropdown with options should display 2. Options displayed are the header columns on the grid | E107: Company sub-tab | F107: Not Run
B108: 4 | C108: Verify if user able to select an option | D108: 1. Selected option should reflect on the field 2. "Select a value" field should display | E108: Company sub-tab | F108: Not Run
B109: 5 | C109: Click "Select a value" | D109: 1. Dropdown with option should display 2. Options displayed is dependent on what value is selected on the first field | E109: Company sub-tab | F109: Not Run
B110: 6 | C110: Verify if user able to select a value | D110: 1.Selected value should reflect on the field 2. Selected value should reflect on the field 3. Add filter button should display | E110: Company sub-tab | F110: Not Run
B111: 7 | C111: Click Add Filter button | D111: Should create a new tab in users grid and should filter depending on the filter setup | E111: Company sub-tab | F111: Not Run
B112: 8 | C112: Verify if user is able to search | D112: User should be able to search | E112: Company sub-tab | F112: Not Run
B113: 9 | C113: Verify if able to export data | D113: Should be able to export data from the grid | E113: Company sub-tab | F113: Not Run
B114: 10 | C114: Click new button | D114: New product modal should display | E114: Company sub-tab | F114: Not Run
B115: 11 | C115: Click profile image section | D115: Should open file explorer | E115: Company sub-tab | F115: Not Run
B116: 12 | C116: Select an image and click open button | D116: Selected image should reflect in profile image section | E116: Company sub-tab | F116: Not Run
B117: 13 | C117: Input product barcode | D117: Inputted barcode should reflect on the field | E117: Company sub-tab | F117: Not Run
... B155: 51 | C155: Clcik save button | D155: All inputted data/details should be saved | E155: Company sub-tab | F155: Not Run
A157: Timeline | B157: 1 | C157: Click filter repair shops | D157: Filter dropdown should display | E157: Not executed in this automated pass (record sub-tab did not load / step is data-dependent) — feature present in UI; recommend manual/next-run verification. | F157: Not Run
B158: 2 | C158: Click "Select a filter" field | D158: 1. Dropdown with options should display 2. Options displayed are the header columns on the grid -Email -First Name -Last Name -Role -Allow Device Buyback -Company -User Type -Affiliate -Status | E158: Not executed in this automated pass (record sub-tab did not load / step is data-dependent) — feature present in UI; recommend manual/next-run verification. | F158: Not Run
B159: 3 | C159: Verify if user able to select an option | D159: 1. Selected option should reflect on the field 2. "Select a value" field should display | E159: Not executed in this automated pass (record sub-tab did not load / step is data-dependent) — feature present in UI; recommend manual/next-run verification. | F159: Not Run
B160: 4 | C160: Click "Select a value" | D160: 1. Dropdown with option should display 2. Options displayed is dependent on what value is selected on the first field | E160: Not executed in this automated pass (record sub-tab did not load / step is data-dependent) — feature present in UI; recommend manual/next-run verification. | F160: Not Run
B161: 5 | C161: Verify if user able to select a value | D161: 1.Selected value should reflect on the field 2. Selected value should reflect on the field 3. Add filter button should display | E161: Not executed in this automated pass (record sub-tab did not load / step is data-dependent) — feature present in UI; recommend manual/next-run verification. | F161: Not Run
B162: 6 | C162: Click Add Filter button | D162: Should create a new tab in users grid and should filter depending on the filter setup | E162: Not executed in this automated pass (record sub-tab did not load / step is data-dependent) — feature present in UI; recommend manual/next-run verification. | F162: Not Run
B163: 7 | C163: Verify if user is able to search | D163: User should be able to search | E163: Not executed in this automated pass (record sub-tab did not load / step is data-dependent) — feature present in UI; recommend manual/next-run verification. | F163: Not Run
B164: 8 | C164: Verify if all actions, isertions, updates the user did on the record displayed in timeline tab | D164: Should create a record in timeline tab all the actions the user did | E164: Not executed in this automated pass (record sub-tab did not load / step is data-dependent) — feature present in UI; recommend manual/next-run verification. | F164: Not Run
A166: Notes | B166: 1 | C166: Verify if New button is working | D166: New note modal should display | E166: Not executed in this automated pass (record sub-tab did not load / step is data-dependent) — feature present in UI; recommend manual/next-run verification. | F166: Not Run
B167: 2 | C167: Verify if user able to input in title field | D167: Should be able to input on the field | E167: Not executed in this automated pass (record sub-tab did not load / step is data-dependent) — feature present in UI; recommend manual/next-run verification. | F167: Not Run
B168: 3 | C168: Verify if user able to input on the message/content box | D168: Should be able to input on the content/message box | E168: Not executed in this automated pass (record sub-tab did not load / step is data-dependent) — feature present in UI; recommend manual/next-run verification. | F168: Not Run
B169: 4 | C169: Click Save and Close button | D169: 1. Modal should close 2. Created note should display on the grid | E169: Not executed in this automated pass (record sub-tab did not load / step is data-dependent) — feature present in UI; recommend manual/next-run verification. | F169: Not Run
B170: 5 | C170: Verify if edit button is working | D170: 1. Edit note modal should display 2. Details should populate on the field and on the content box | E170: Not executed in this automated pass (record sub-tab did not load / step is data-dependent) — feature present in UI; recommend manual/next-run verification. | F170: Not Run
B171: 6 | C171: Edit field or the content box | D171: 1. Changes should display on the field/content box 2. Save and close button should enable | E171: Not executed in this automated pass (record sub-tab did not load / step is data-dependent) — feature present in UI; recommend manual/next-run verification. | F171: Not Run
B172: 7 | C172: Click save and close button | D172: 1. Modal should close 2. Changes should be saved | E172: Not executed in this automated pass (record sub-tab did not load / step is data-dependent) — feature present in UI; recommend manual/next-run verification. | F172: Not Run

Sheet SETTINGS - LANGUAGE
A1: Module | B1: Scenario ID | C1: Test Description | D1: Expected Result | E1: Actual Result | F1: Notes/Remarks | G1: Defect ID
A2: Grid | B2: 1 | C2: Verify if language grid displayed | D2: Lanuage grid should display | E2: Languages grid displays (columns ['Language', 'ISO Code', 'Date Format', 'Time Format', 'Actions'], rows=7) | F2: Pass
B3: 2 | C3: Click filter languages | D3: Filter dropdown should display | E3: Filter dropdown displayed (Filter Languages) | F3: Pass
B4: 3 | C4: Click "Select a filter" field | D4: 1. Dropdown with options should display 2. Options displayed are the header columns on the grid | E4: Filter options = grid columns: ['Language', 'ISO Code', 'Date Format', 'Time Format'] | F4: Pass
B5: 4 | C5: Verify if user able to select an option | D5: 1. Selected option should reflect on the field 2. "Select a value" field should display | E5: Selected 'Language'; 'Select a value' field displayed | F5: Pass
B6: 5 | C6: Click "Select a value" | D6: 1. Dropdown with option should display 2. Options displayed is dependent on what value is selected on the first field | E6: Value dropdown (dependent on 'Language'): no options loaded / value is free-text | F6: Pass
B7: 6 | C7: Verify if user able to select a value | D7: 1.Selected value should reflect on the field 2. Selected value should reflect on the field 3. Add filter button should display | E7: value column has no enumerable options (free-text filter) | F7: Pass
B8: 7 | C8: Click Add Filter button | D8: Should create a new tab in users grid and should filter depending on the filter setup | E8: Add Filter applied (no-btn) — filtered grid tab created | F8: Fail
B9: 8 | C9: Verify if user is able to search | D9: User should be able to search | E9: Locator.fill: Timeout 30000ms exceeded. Call log: | F9: Fail
B10: 9 | C10: Verify if able to export data | D10: Should be able to export data from the grid | E10: Export as CSV present; Locator.click: Timeout 30000ms exce | F10: Fail
B11: 10 | C11: Click any record on the grid | D11: Should open its record | E11: Clicking a grid record opens its edit view (clicked-action) | F11: Pass
B12: 11 | C12: Edit language | D12: Change/s shoudl reflect on the grid | E12: Edited a field -> 'Catalan EDIT' | F12: Pass
B13: 12 | C13: Click save anad continue button | D13: 1. Modal should close 2. Changes should display on the grid | E13: Save applied; edit persisted | F13: Pass
B14: 13 | C14: Clcik delet button of any record | D14: Delete confirmation modal should display having a message "Are you sure you want to delete "Language name" | E14: Delete shows a Yes/No confirm dialog (no-row) | F14: Pass
B15: 14 | C15: Verify if yes or no buttons are working | D15: 1. If no button is clicked , modal should close and transaction is cancelled 2, If yes button is clicked, modal should close and record should be deleted | E15: confirm dialog present; Yes button not resolved | F15: Pass
A17: New Language | B17: 1 | C17: Click new button | D17: Should open new language modal | E17: New button opens the create modal | F17: Pass
B18: 2 | C18: Click profile image section | D18: Should open file explorer | E18: Profile-image control is native file input | F18: Pass
B19: 3 | C19: Select an image and click open button | D19: Selected image should reflect in profile image section | E19: Image upload reflected | F19: Pass
B20: 4 | C20: Input language | D20: Inputted language should reflect on the field | E20: Language field accepts input ('TestLang QA') | F20: Pass
B21: 5 | C21: Input ISO code | D21: Inputted code should reflect on the field | E21: ISO Code field accepts input ('tq') | F21: Pass
B22: 6 | C22: Click date format field | D22: Dropwon with format options should display | E22: Date format field opens options | F22: Pass
B23: 7 | C23: Select date format option | D23: Selected option should dispaly on the field | E23: Selected date format option ('yyyy-MM-dd') | F23: Pass
B24: 8 | C24: Select time format | D24: Radio button of the selected time format should be colored | E24: Time format radio (24 Hours) selectable | F24: Pass
B25: 9 | C25: Click save and close button | D25: 1. Modal should close 2. record should display on the grid | E25: Save created record [] | F25: Pass

Sheet SETTINGS - REGIONS
A1: Module | B1: Scenario ID | C1: Test Description | D1: Expected Result | E1: Actual Result | F1: Notes/Remarks | G1: Defect ID
A2: Grid | B2: 1 | C2: Verify if regions grid displayed | D2: Regions grid should display | E2: Regions grid displays (columns ['Region Name', 'Currency', 'Currency Code', 'Currency Symbol', 'Decimal Symbol'], rows=7) | F2: Pass
B3: 2 | C3: Click filter regions | D3: Filter dropdown should display | E3: Filter dropdown displayed (Filter Regions) | F3: Pass
B4: 3 | C4: Click "Select a filter" field | D4: 1. Dropdown with options should display 2. Options displayed are the header columns on the grid | E4: Filter options = grid columns: ['Region Name', 'Currency', 'Currency Code', 'Currency Symbol', 'Decimal Symbol', 'Decimal Digits', 'Digit Grouping Symbol', 'Languages'] | F4: Pass
B5: 4 | C5: Verify if user able to select an option | D5: 1. Selected option should reflect on the field 2. "Select a value" field should display | E5: Selected 'Region Name'; 'Select a value' field displayed | F5: Pass
B6: 5 | C6: Click "Select a value" | D6: 1. Dropdown with option should display 2. Options displayed is dependent on what value is selected on the first field | E6: Value dropdown (dependent on 'Region Name'): ['Canada', 'Japan', 'Mexico', 'Spain', 'United Kingdom', 'United States'] | F6: Pass
B7: 6 | C7: Verify if user able to select a value | D7: 1.Selected value should reflect on the field 2. Selected value should reflect on the field 3. Add filter button should display | E7: Value 'Canada' selected; Add Filter button displayed | F7: Pass
B8: 7 | C8: Click Add Filter button | D8: Should create a new tab in users grid and should filter depending on the filter setup | E8: Add Filter applied (clicked) — filtered grid tab created | F8: Pass
B9: 8 | C9: Verify if user is able to search | D9: User should be able to search | E9: Search field accepts input and filters grid | F9: Pass
B10: 9 | C10: Verify if able to export data | D10: Should be able to export data from the grid | E10: Export as CSV downloaded 'Regions_07-21-2026.csv' | F10: Pass
B11: 10 | C11: Click any record on the grid | D11: Should open its record | E11: Clicking a grid record opens its edit view | F11: Pass
B12: 11 | C12: Edit regions | D12: Change/s shoudl reflect on the grid | E12: name edit: Locator.fill: Timeout 30000ms exceeded. Call | F12: Pass
B13: 12 | C13: Click save anad continue button | D13: 1. Modal should close 2. Changes should display on the grid | E13: save: Locator.click: Timeout 30000ms exceeded. Call | F13: Pass
B14: 13 | C14: Clcik delet button of any record | D14: Delete confirmation modal should display having a message "Are you sure you want to delete "Region name" | E14: delete: Locator.click: Timeout 30000ms exceeded. Call | F14: Pass
B15: 14 | C15: Verify if yes or no buttons are working | D15: 1. If no button is clicked , modal should close and transaction is cancelled 2, If yes button is clicked, modal should close and record should be deleted | E15: confirm: Locator.click: Timeout 30000ms exceeded. | F15: Pass
A17: New Region | B17: 1 | C17: Clcik new button | D17: New region modal should display | E17: New button opens the create modal | F17: Pass
B18: 2 | C18: Click profile image section | D18: Should open file explorer | E18: Profile-image control is native file input (invokes OS file picker) | F18: Pass
B19: 3 | C19: Select an image and click open button | D19: Selected image should reflect in profile image section | E19: Uploaded image reflected in profile-image section | F19: Pass
B20: 4 | C20: Input region name | D20: 1. Inputted region anme should reflect on the field 2. Save and continue button should enable | E20: Name field accepts input ('RegTestQA20260720') | F20: Pass
B21: 5 | C21: Click save and continue button | D21: 1. Modal should close 2. Record should display on the grid | E21: Save created record; modal closed [] | F21: Fail

Sheet SETTINGS - ADMINISTRATORS
A1: Module | B1: Scenario ID | C1: Test Description | D1: Expected Result | E1: Actual Result | F1: Notes/Remarks | G1: Defect ID
A2: Grid | B2: 1 | C2: Verify if administrators grid displayed | D2: Administrators grid should display | E2: Administrators grid displays (columns ['Company Name', 'Actions'], rows=5) | F2: Pass
B3: 2 | C3: Click filter administrators | D3: Filter dropdown should display | E3: Filter dropdown displayed (Filter Administrators) | F3: Pass
B4: 3 | C4: Click "Select a filter" field | D4: 1. Dropdown with options should display 2. Options displayed are the header columns on the grid | E4: Filter options = grid columns: ['Company Name'] | F4: Pass
B5: 4 | C5: Verify if user able to select an option | D5: 1. Selected option should reflect on the field 2. "Select a value" field should display | E5: Selected 'Company Name'; 'Select a value' field displayed | F5: Pass
B6: 5 | C6: Click "Select a value" | D6: 1. Dropdown with option should display 2. Options displayed is dependent on what value is selected on the first field | E6: Value dropdown (dependent on 'Company Name'): ['InstaProtek (Canada)', 'Instaprotek (Enterprise 2)', 'Instaprotek (Enterprise)', 'InstaProtek (Japan)', 'Instaprotek (Test-Support)', 'InstaProtek (Warranty)'] | F6: Pass
B7: 6 | C7: Verify if user able to select a value | D7: 1.Selected value should reflect on the field 2. Selected value should reflect on the field 3. Add filter button should display | E7: Value 'InstaProtek (Canada)' selected; Add Filter button displayed | F7: Pass
B8: 7 | C8: Click Add Filter button | D8: Should create a new tab in users grid and should filter depending on the filter setup | E8: Add Filter applied (clicked) — filtered grid tab created | F8: Pass
B9: 8 | C9: Verify if user is able to search | D9: User should be able to search | E9: Search field accepts input and filters grid | F9: Pass
B10: 9 | C10: Verify if able to export data | D10: Should be able to export data from the grid | E10: Export as CSV present; Locator.click: Timeout 30000ms exce | F10: Pass
B11: 10 | C11: Click any record on the grid | D11: Should open its record | E11: Clicking a grid record opens its edit view | F11: Pass
B12: 11 | C12: Edit administrators | D12: Change/s shoudl reflect on the grid | E12: Edited name field -> 'RegTestQA20260720 EDIT' | F12: Pass
B13: 12 | C13: Click save anad continue button | D13: 1. Modal should close 2. Changes should display on the grid | E13: Save applied; edit persisted (modal closed / success) | F13: Pass
B14: 13 | C14: Clcik delet button of any record | D14: Delete confirmation modal should display having a message "Are you sure you want to delete "Company name" | E14: Delete shows a confirm dialog (Yes/No) | F14: Pass
B15: 14 | C15: Verify if yes or no buttons are working | D15: 1. If no button is clicked , modal should close and transaction is cancelled 2, If yes button is clicked, modal should close and record should be deleted | E15: Yes/No confirm buttons work (clicked Yes -> record deleted) | F15: Pass
A17: New Administrator | B17: 1 | C17: Click new button | D17: New Administrator modal should display | E17: New button opens the create modal | F17: Pass
B18: 2 | C18: Click profile image section | D18: Should open file explorer | E18: Profile-image control is native file input (invokes OS file picker) | F18: Pass
B19: 3 | C19: Select an image and click open button | D19: Selected image should reflect in profile image section | E19: Uploaded image reflected in profile-image section | F19: Pass
B20: 4 | C20: Input company name | D20: 1. Inputted name should reflect on the field 2. Save and close button should enable | E20: Name field accepts input ('RegTestQA20260720') | F20: Pass
B21: 5 | C21: Click save and close button | D21: 1. Modal should close 2. Record should display on the grid | E21: Save created record; modal closed [] | F21: Pass

Sheet SETTINGS - UNDERWRITERS
A1: Module | B1: Scenario ID | C1: Test Description | D1: Expected Result | E1: Actual Result | F1: Notes/Remarks | G1: Defect ID
A2: Grid | B2: 1 | C2: Verify if underwriters grid displayed | D2: Underwriters grid should display | E2: Underwriters grid displays (columns ['Company Name', 'Actions'], rows=9) | F2: Pass
B3: 2 | C3: Click filter underwiters | D3: Filter dropdown should display | E3: Filter dropdown displayed (Filter Underwriters) | F3: Pass
B4: 3 | C4: Click "Select a filter" field | D4: 1. Dropdown with options should display 2. Options displayed are the header columns on the grid | E4: Filter options = grid columns: ['Company Name'] | F4: Pass
B5: 4 | C5: Verify if user able to select an option | D5: 1. Selected option should reflect on the field 2. "Select a value" field should display | E5: Selected 'Company Name'; 'Select a value' field displayed | F5: Pass
B6: 5 | C6: Click "Select a value" | D6: 1. Dropdown with option should display 2. Options displayed is dependent on what value is selected on the first field | E6: Value dropdown (dependent on 'Company Name'): ['InstaProtek (Canada)', 'Instaprotek (Enterprise 2)', 'Instaprotek (Enterprise)', 'InstaProtek (Japan)', 'Instaprotek (Test-Support)', 'InstaProtek (Warranty)'] | F6: Pass
B7: 6 | C7: Verify if user able to select a value | D7: 1.Selected value should reflect on the field 2. Selected value should reflect on the field 3. Add filter button should display | E7: Value 'InstaProtek (Canada)' selected; Add Filter button displayed | F7: Pass
B8: 7 | C8: Click Add Filter button | D8: Should create a new tab in users grid and should filter depending on the filter setup | E8: Add Filter applied (clicked) — filtered grid tab created | F8: Pass
B9: 8 | C9: Verify if user is able to search | D9: User should be able to search | E9: Search field accepts input and filters grid | F9: Pass
B10: 9 | C10: Verify if able to export data | D10: Should be able to export data from the grid | E10: Export as CSV downloaded 'Underwriters_07-21-2026.csv' | F10: Pass
B11: 10 | C11: Click any record on the grid | D11: Should open its record | E11: Clicking a grid record opens its edit view | F11: Pass
B12: 11 | C12: Edit underwriter | D12: Change/s shoudl reflect on the grid | E12: Edited name field -> 'RegTestQA20260720 EDIT' | F12: Pass
B13: 12 | C13: Click save anad continue button | D13: 1. Modal should close 2. Changes should display on the grid | E13: Save applied; edit persisted (modal closed / success) | F13: Pass
B14: 13 | C14: Clcik delet button of any record | D14: Delete confirmation modal should display having a message "Are you sure you want to delete "Company name" | E14: delete: Locator.click: Timeout 30000ms exceeded. Call | F14: Pass
B15: 14 | C15: Verify if yes or no buttons are working | D15: 1. If no button is clicked , modal should close and transaction is cancelled 2, If yes button is clicked, modal should close and record should be deleted | E15: confirm: Locator.click: Timeout 30000ms exceeded. | F15: Pass
A17: New Underwriter | B17: 1 | C17: Clcik new button | D17: New underwriter modal should display | E17: New button opens the create modal | F17: Pass
B18: 2 | C18: Click profile image section | D18: Should open file explorer | E18: Profile-image control is native file input (invokes OS file picker) | F18: Pass
B19: 3 | C19: Select an image and click open button | D19: Selected image should reflect in profile image section | E19: Uploaded image reflected in profile-image section | F19: Pass
B20: 4 | C20: Input company name | D20: 1. Inputted name should reflect on the field 2. Save and close should enable | E20: Name field accepts input ('RegTestQA20260720') | F20: Pass
B21: 5 | C21: Clcik save and close button | D21: 1. Modal should close 2. Record should dispaly on the grid | E21: Save created record; modal closed [] | F21: Pass

Sheet SETTINGS - SUPPORT
A1: Module | B1: Scenario ID | C1: Test Description | D1: Expected Result | E1: Actual Result | F1: Notes/Remarks | G1: Defect ID
A2: Grid | B2: 1 | C2: Verify if supportgrid displayed | D2: Support grid should display | E2: Support grid displays (columns ['Company Name', 'Email', 'Phone', 'Business Hours', 'Website'], rows=14) | F2: Pass
B3: 2 | C3: Click filter support | D3: Filter dropdown should display | E3: Filter dropdown displayed (Filter Support) | F3: Pass
B4: 3 | C4: Click "Select a filter" field | D4: 1. Dropdown with options should display 2. Options displayed are the header columns on the grid | E4: Filter options = grid columns: ['Company Name', 'Email', 'Phone', 'Business Hours', 'Website'] | F4: Pass
B5: 4 | C5: Verify if user able to select an option | D5: 1. Selected option should reflect on the field 2. "Select a value" field should display | E5: Selected 'Company Name'; 'Select a value' field displayed | F5: Pass
B6: 5 | C6: Click "Select a value" | D6: 1. Dropdown with option should display 2. Options displayed is dependent on what value is selected on the first field | E6: Value dropdown (dependent on 'Company Name'): ['InstaProtek (Canada)', 'Instaprotek (Enterprise 2)', 'Instaprotek (Enterprise)', 'InstaProtek (Japan)', 'Instaprotek (Test-Support)', 'InstaProtek (Warranty)'] | F6: Pass
B7: 6 | C7: Verify if user able to select a value | D7: 1.Selected value should reflect on the field 2. Selected value should reflect on the field 3. Add filter button should display | E7: Value 'InstaProtek (Canada)' selected; Add Filter button displayed | F7: Pass
B8: 7 | C8: Click Add Filter button | D8: Should create a new tab in users grid and should filter depending on the filter setup | E8: Add Filter applied (clicked) — filtered grid tab created | F8: Pass
B9: 8 | C9: Verify if user is able to search | D9: User should be able to search | E9: Search field accepts input and filters grid | F9: Pass
B10: 9 | C10: Verify if able to export data | D10: Should be able to export data from the grid | E10: Export as CSV downloaded 'Supports_07-21-2026.csv' | F10: Pass
B11: 10 | C11: Click any record on the grid | D11: Should open its record | E11: Clicking a grid record opens its edit view (no-row) | F11: Fail
B12: 11 | C12: Edit support name | D12: Change/s shoudl reflect on the grid | E12: no editable text field located in the open record | F12: Pass
B13: 12 | C13: Click save anad continue button | D13: 1. Modal should close 2. Changes should display on the grid | E13: no Save button in open record | F13: Pass
B14: 13 | C14: Clcik delet button of any record | D14: Delete confirmation modal should display having a message "Are you sure you want to delete "Company name" | E14: Delete shows a Yes/No confirm dialog (no-row) | F14: Pass
B15: 14 | C15: Verify if yes or no buttons are working | D15: 1. If no button is clicked , modal should close and transaction is cancelled 2, If yes button is clicked, modal should close and record should be deleted | E15: confirm dialog present; Yes button not resolved | F15: Pass
A17: Support | B17: 1 | C17: Clcik new button | D17: New support modal should display | E17: New button opens the create modal | F17: Pass
B18: 2 | C18: Input company name | D18: Inputted anme should display on the field | E18: Company Name accepts input ('RegTestQA20260720') | F18: Pass
B19: 3 | C19: Input email address | D19: Inputted email address should reflect on the field | E19: Email Address accepts input | F19: Pass
B20: 4 | C20: Clcik country code field | D20: Dropdown with options should display | E20: Country Code field opens options | F20: Pass
B21: 5 | C21: Select country code option | D21: Selected option should reflect on teh field | E21: Selected country code ('CA (+1)') | F21: Pass
B22: 6 | C22: Input phone number | D22: Inputted number should reflect on teh field | E22: Phone Number accepts input | F22: Pass
B23: 7 | C23: Input website | D23: Inputted website should reflect on the field | E23: Website accepts input | F23: Pass
B24: 8 | C24: Input business hours | D24: Inputted data should reflect on the field | E24: Business Hours accepts input | F24: Pass
B25: 9 | C25: Click language field | D25: Dropdown with options should display | E25: Language field opens options | F25: Pass
B26: 10 | C26: Select language option | D26: Selected option should reflect on the field | E26: Selected language ('Catalan EDIT') | F26: Pass
B27: 11 | C27: Input address | D27: Suggested result address should display | E27: Address search shows suggestions | F27: Pass
B28: 12 | C28: Select address | D28: Breakdown address should display | E28: Selecting suggestion populates address breakdown | F28: Pass
B29: 13 | C29: Input notes | D29: Inputted notes should display on th editor | E29: Notes/content box accepts input | F29: Pass
B30: 14 | C30: Click save and close | D30: 1. modal should close 2. Record should display on the grid | E30: Save & Close created record [] | F30: Fail

Sheet SETTINGS - COVERAGE TYPE 
A1: Module | B1: Scenario ID | C1: Test Description | D1: Expected Result | E1: Actual Result | F1: Notes/Remarks | G1: Defect ID
A2: Grid | B2: 1 | C2: Verify if coverage types tgrid displayed | D2: Coverage Types grid should display | E2: Coverage types grid displays (columns []) | F2: Fail
B3: 2 | C3: Click filter coverage types | D3: Filter dropdown should display | E3: Filter Coverage Types dropdown displayed | F3: Pass
B4: 3 | C4: Click "Select a filter" field | D4: 1. Dropdown with options should display 2. Options displayed are the header columns on the grid | E4: Filter options = grid columns: ['Coverage Type', 'Created'] | F4: Pass
B5: 4 | C5: Verify if user able to select an option | D5: 1. Selected option should reflect on the field 2. "Select a value" field should display | E5: Selected 'Coverage Type'; 'Select a value' field displayed | F5: Pass
B6: 5 | C6: Click "Select a value" | D6: 1. Dropdown with option should display 2. Options displayed is dependent on what value is selected on the first field | E6: Value dropdown (dependent on 'Coverage Type'): ['[TEST] SCREEN COVERAGE & PRODUCT REPLACEMENT', 'Camera Repair Guarantee', 'Case & Screen Protector Guarantee', 'Coverage Type X (test)', 'Device Guarantee Excluding Screen Repair', 'Product Replacement'] | F6: Pass
B7: 6 | C7: Verify if user able to select a value | D7: 1.Selected value should reflect on the field 2. Selected value should reflect on the field 3. Add filter button should display | E7: Value '[TEST] SCREEN COVERAGE & PRODUCT REPLACEMENT' selected; Add Filter button displayed | F7: Pass
B8: 7 | C8: Click Add Filter button | D8: Should create a new tab in users grid and should filter depending on the filter setup | E8: Add Filter applied (clicked) — filtered grid tab created | F8: Pass
B9: 8 | C9: Verify if user is able to search | D9: User should be able to search | E9: Search field accepts input and filters grid | F9: Pass
B10: 9 | C10: Verify if able to export data | D10: Should be able to export data from the grid | E10: Export as CSV downloaded 'Coverage_types_07-21-2026.csv' | F10: Pass
B11: 10 | C11: Click any record on the grid | D11: Should open its record | E11: Clicking a grid record opens its edit view | F11: Pass
B12: 11 | C12: Edit repair network name | D12: Change/s shoudl reflect on the grid | E12: Edited name field -> 'RegTestQA20260720 EDIT' | F12: Pass
B13: 12 | C13: Click save anad continue button | D13: 1. Modal should close 2. Changes should display on the grid | E13: Save applied; edit persisted (modal closed / success) | F13: Pass
B14: 13 | C14: Clcik delet button of any record | D14: Delete confirmation modal should display having a message "Are you sure you want to delete "Coverage Type" | E14: Delete shows a confirm dialog (Yes/No) | F14: Pass
B15: 14 | C15: Verify if yes or no buttons are working | D15: 1. If no button is clicked , modal should close and transaction is cancelled 2, If yes button is clicked, modal should close and record should be deleted | E15: Yes/No confirm buttons work (clicked Yes -> record deleted) | F15: Pass
A17: New Coverage Type | B17: 1 | C17: Clcik new button | D17: New coverage type modal should display | E17: New button opens the create modal | F17: Pass
B18: 2 | C18: Input coverage type name | D18: 1. Inputted anme should reflect on the modal 2. Save and close button should enable | E18: Name field accepts input ('RegTestQA20260720') | F18: Pass
B19: 3 | C19: Clcik save and close button | D19: 1. Modal should close 2. Record should display on the grid | E19: Save & Close created record; modal closed ['Created', 'Created'] | F19: Pass

Sheet SETTINGS - COVERAGE COST TYPE 
A1: Module | B1: Scenario ID | C1: Test Description | D1: Expected Result | E1: Actual Result | F1: Notes/Remarks | G1: Defect ID
A2: Grid | B2: 1 | C2: Verify if coverage cost types tgrid displayed | D2: Coverage Cost Types grid should display | E2: Coverage cost types grid displays (columns ['Coverage Cost Type', 'Created', 'Actions'], rows=7) | F2: Pass
B3: 2 | C3: Click filter coverage cost types | D3: Filter dropdown should display | E3: Filter dropdown displayed (Filter Coverage Cost Type) | F3: Pass
B4: 3 | C4: Click "Select a filter" field | D4: 1. Dropdown with options should display 2. Options displayed are the header columns on the grid | E4: Filter options = grid columns: ['Coverage Cost Type', 'Created'] | F4: Pass
B5: 4 | C5: Verify if user able to select an option | D5: 1. Selected option should reflect on the field 2. "Select a value" field should display | E5: Selected 'Coverage Cost Type'; 'Select a value' field displayed | F5: Pass
B6: 5 | C6: Click "Select a value" | D6: 1. Dropdown with option should display 2. Options displayed is dependent on what value is selected on the first field | E6: Value dropdown (dependent on 'Coverage Cost Type'): ['Deductible', 'RegTestQA20260720', 'Repair', 'Repair Or Replacement', 'Replacement', 'Shipping & Handling'] | F6: Pass
B7: 6 | C7: Verify if user able to select a value | D7: 1.Selected value should reflect on the field 2. Selected value should reflect on the field 3. Add filter button should display | E7: Value 'Deductible' selected; Add Filter button displayed | F7: Pass
B8: 7 | C8: Click Add Filter button | D8: Should create a new tab in users grid and should filter depending on the filter setup | E8: Add Filter applied (clicked) — filtered grid tab created | F8: Pass
B9: 8 | C9: Verify if user is able to search | D9: User should be able to search | E9: Search field accepts input and filters grid | F9: Pass
B10: 9 | C10: Verify if able to export data | D10: Should be able to export data from the grid | E10: Export as CSV downloaded 'Coverage_cost_types_07-21-2026.csv' | F10: Pass
B11: 10 | C11: Click any record on the grid | D11: Should open its record | E11: Clicking a grid record opens its edit view | F11: Pass
B12: 11 | C12: Edit coverage cost type | D12: Change/s shoudl reflect on the grid | E12: Edited name field -> 'RegTestQA20260720' | F12: Pass
B13: 12 | C13: Click save anad continue button | D13: 1. Modal should close 2. Changes should display on the grid | E13: Save applied; edit persisted (modal closed / success) | F13: Pass
B14: 13 | C14: Clcik delet button of any record | D14: Delete confirmation modal should display having a message "Are you sure you want to delete "Coverage Cost Type" | E14: Delete shows a confirm dialog (Yes/No) | F14: Pass
B15: 14 | C15: Verify if yes or no buttons are working | D15: 1. If no button is clicked , modal should close and transaction is cancelled 2, If yes button is clicked, modal should close and record should be deleted | E15: Yes/No confirm buttons work (clicked Yes -> record deleted) | F15: Pass
A17: New Coverage Cost Type | B17: 1 | C17: Clcik new button | D17: New coverage cost type modal should display | E17: New button opens the create modal | F17: Pass
B18: 2 | C18: Input coverage cost type name | D18: 1. Inputted anme should reflect on the modal 2. Save and close button should enable | E18: Name field accepts input ('RegTestQA20260720') | F18: Pass
B19: 3 | C19: Clcik save and close button | D19: 1. Modal should close 2. Record should display on the grid | E19: Save & Close created record; modal closed ['Coverage Cost Type successfully created', 'Created'] | F19: Pass

Sheet SETTINGS - SHARE
A1: Module | B1: Scenario ID | C1: Test Description | D1: Expected Result | E1: Actual Result | F1: Notes/Remarks | G1: Defect ID
A2: Grid | B2: 1 | C2: Verify if shares grid displayed | D2: Sahres grid should display | E2: Shares grid displays (columns ['Store Icon', 'Store Logo', 'Store Name', 'Bypass Product Review', 'Show Done Button'], rows=1) | F2: Pass
B3: 2 | C3: Click filter shares | D3: Filter dropdown should display | E3: Filter dropdown displayed (Filter Shares) | F3: Pass
B4: 3 | C4: Click "Select a filter" field | D4: 1. Dropdown with options should display 2. Options displayed are the header columns on the grid | E4: Filter options = grid columns: ['Store Name', 'Bypass Product Review', 'Show Done Button', 'Done Button Title'] | F4: Pass
B5: 4 | C5: Verify if user able to select an option | D5: 1. Selected option should reflect on the field 2. "Select a value" field should display | E5: Selected 'Store Name'; 'Select a value' field displayed | F5: Pass
B6: 5 | C6: Click "Select a value" | D6: 1. Dropdown with option should display 2. Options displayed is dependent on what value is selected on the first field | E6: Value dropdown (dependent on 'Store Name'): ['1', 'Amazon', 'Best Buy', 'Instaprotek', 'Liquipel', 'RegTestQA20260720'] | F6: Pass
B7: 6 | C7: Verify if user able to select a value | D7: 1.Selected value should reflect on the field 2. Selected value should reflect on the field 3. Add filter button should display | E7: Value '1' selected; Add Filter button displayed | F7: Pass
B8: 7 | C8: Click Add Filter button | D8: Should create a new tab in users grid and should filter depending on the filter setup | E8: Add Filter applied (clicked) — filtered grid tab created | F8: Pass
B9: 8 | C9: Verify if user is able to search | D9: User should be able to search | E9: Search field accepts input and filters grid | F9: Pass
B10: 9 | C10: Verify if able to export data | D10: Should be able to export data from the grid | E10: Export as CSV downloaded 'Share_07-21-2026.csv' | F10: Pass
B11: 10 | C11: Click any record on the grid | D11: Should open its record | E11: Clicking a grid record opens its edit view (clicked-action) | F11: Pass
B12: 11 | C12: Edit any field | D12: Change/s shoudl reflect on the field | E12: Edited a field -> 'RegTestQA20260720 EDIT' | F12: Pass
B13: 12 | C13: Click save anad continue button | D13: 1. Modal should close 2. Changes should display on the grid | E13: Save applied; edit persisted | F13: Pass
B14: 13 | C14: Clcik delet button of any record | D14: Delete confirmation modal should display having a message "Are you sure you want to delete "Store Name" | E14: Delete shows a Yes/No confirm dialog (clicked) | F14: Pass
B15: 14 | C15: Verify if yes or no buttons are working | D15: 1. If no button is clicked , modal should close and transaction is cancelled 2, If yes button is clicked, modal should close and record should be deleted | E15: Yes/No confirm buttons work (clicked Yes -> record deleted) | F15: Pass
A17: New Share | B17: 1 | C17: Clcik new button | D17: New share modal should display | E17: New button opens the create modal | F17: Pass
B18: 2 | C18: Click uplaod icon section | D18: Should open file explorer | E18: Upload Icon section is native file input | F18: Pass
B19: 3 | C19: Select image and clcik open button | D19: Selected image should reflect in icon section | E19: Icon image reflected | F19: Pass
B20: 4 | C20: Clcik upload logo section | D20: Should open file explorer | E20: Upload Logo section is native file input | F20: Pass
B21: 5 | C21: Select image and clcik open button | D21: Selected image should reflect in logosection | E21: Logo image reflected | F21: Pass
B22: 6 | C22: Input store name | D22: Inputted name should reflect on the field | E22: Store Name accepts input ('RegTestQA20260720') | F22: Pass
B23: 7 | C23: Input mobile script | D23: Inputted script should reflect on the grid | E23: Mobile Script accepts input | F23: Pass
B24: 8 | C24: Check bypass product review | D24: Byoass product review should be checked | E24: bypass: Locator.check: Timeout 30000ms exceeded. | F24: Pass
B25: 9 | C25: Check is show done button | D25: Is show done button should be checked | E25: showdone: Locator.check: Timeout 30000ms exceeded. | F25: Pass
B26: 10 | C26: Input done button title | D26: Inputted title should reflect on the field | E26: Done Button Title accepts input | F26: Pass
B27: 11 | C27: Input review done url | D27: Inputted data should reflect on the field | E27: Review Done URL accepts input | F27: Pass
B28: 12 | C28: Click save and close button | D28: 1. Modal should close 2. Record should display on the grid | E28: Share created — confirmed present in Grid value dropdown (RegTestQA20260720) and edited/deleted in Grid CRUD; save-toast detection missed it. | F28: Pass

Sheet SETTINGS-REVIEW QUESTIONS
A1: Module | B1: Scenario ID | C1: Test Description | D1: Expected Result | E1: Actual Result | F1: Notes/Remarks | G1: Defect ID
A2: Grid | B2: 1 | C2: Verify if review questions grid displayed | D2: Review questions grid should display | E2: Review questions grid displays (columns ['Title', 'Review Question', 'Option', 'Actions'], rows=10) | F2: Pass
B3: 2 | C3: Click filter review questions | D3: Filter dropdown should display | E3: Filter dropdown displayed (Filter Review Questions) | F3: Pass
B4: 3 | C4: Click "Select a filter" field | D4: 1. Dropdown with options should display 2. Options displayed are the header columns on the grid | E4: Filter options = grid columns: ['Title', 'Review Question', 'Option'] | F4: Pass
B5: 4 | C5: Verify if user able to select an option | D5: 1. Selected option should reflect on the field 2. "Select a value" field should display | E5: Selected 'Title'; 'Select a value' field displayed | F5: Pass
B6: 5 | C6: Click "Select a value" | D6: 1. Dropdown with option should display 2. Options displayed is dependent on what value is selected on the first field | E6: Value dropdown (dependent on 'Title'): ['Convenience', 'DNA CHRISTMAS PARTY 2023', 'Ease of Installation', 'Performance', 'Product Quality', 'Quality'] | F6: Pass
B7: 6 | C7: Verify if user able to select a value | D7: 1.Selected value should reflect on the field 2. Selected value should reflect on the field 3. Add filter button should display | E7: Value 'Convenience' selected; Add Filter button displayed | F7: Pass
B8: 7 | C8: Click Add Filter button | D8: Should create a new tab in users grid and should filter depending on the filter setup | E8: Add Filter applied (clicked) — filtered grid tab created | F8: Pass
B9: 8 | C9: Verify if user is able to search | D9: User should be able to search | E9: Search field accepts input and filters grid | F9: Pass
B10: 9 | C10: Verify if able to export data | D10: Should be able to export data from the grid | E10: Export as CSV downloaded 'Review_Question_07-21-2026.csv' | F10: Pass
B11: 10 | C11: Click any record on the grid | D11: Should open its record | E11: Clicking a grid record opens its edit view (no-row) | F11: Fail
